Workbook
Name POWER_USER_LINK_EDA81D4C_E424_4C6E_8A36_5F1A4994EB75: "Summary!R4C1:R17C2"

Sheet Cover
C7: Title | D7: Project Crystal - JV Day 1 Readiness Plan
C9: Description | D9: All actions required to achieve JV Day-1 operational readiness
C11: Date | D11: =TODAY() -> 46083

Sheet Summary
B2: REQUIREMENTS BY OWNER | C2: =SUM(C4:C28) -> 117 | D2: =SUM(D4:D28) -> 4 | E2: =SUM(E4:E28) -> 89 | F2: =SUM(F4:F28) -> 24 | G2: =SUM(G4:G28) -> 0 | I2: REQUIREMENTS BY CATEGORY | J2: =SUM(J4:J20) -> 119 | K2: =SUM(K4:K20) -> 4 | L2: =SUM(L4:L20) -> 91 | M2: =SUM(M4:M20) -> 24 | N2: =SUM(N4:N20) -> 0
B3: Owner | C3: Total | D3: Completed | E3: Not started | F3: On-track | G3: Delayed | I3: Workstream | J3: Total | K3: Completed | L3: Not started | M3: On-track | N3: Delayed
B4: Hassen Moolla | C4: =SUM(D4:G4) -> 16 | D4: =(COUNTIFS('JV Readiness Plan'!$E:$E,$B4,'JV Readiness Plan'!$F:$F,D$3)) -> 1 | E4: =(COUNTIFS('JV Readiness Plan'!$E:$E,$B4,'JV Readiness Plan'!$F:$F,E$3)) -> 9 | F4: =(COUNTIFS('JV Readiness Plan'!$E:$E,$B4,'JV Readiness Plan'!$F:$F,F$3)) -> 6 | G4: =(COUNTIFS('JV Readiness Plan'!$E:$E,$B4,'JV Readiness Plan'!$F:$F,G$3)) -> 0 | I4: Budget and BP | J4: =SUM(K4:N4) -> 9 | K4: =(COUNTIFS('JV Readiness Plan'!$B:$B,$I4,'JV Readiness Plan'!$F:$F,K$3)) -> 1 | L4: =(COUNTIFS('JV Readiness Plan'!$B:$B,$I4,'JV Readiness Plan'!$F:$F,L$3)) -> 4 | M4: =(COUNTIFS('JV Readiness Plan'!$B:$B,$I4,'JV Readiness Plan'!$F:$F,M$3)) -> 4 | N4: =(COUNTIFS('JV Readiness Plan'!$B:$B,$I4,'JV Readiness Plan'!$F:$F,N$3)) -> 0
B5: Muddassar Khan | C5: =SUM(D5:G5) -> 14 | D5: =(COUNTIFS('JV Readiness Plan'!$E:$E,$B5,'JV Readiness Plan'!$F:$F,D$3)) -> 2 | E5: =(COUNTIFS('JV Readiness Plan'!$E:$E,$B5,'JV Readiness Plan'!$F:$F,E$3)) -> 5 | F5: =(COUNTIFS('JV Readiness Plan'!$E:$E,$B5,'JV Readiness Plan'!$F:$F,F$3)) -> 7 | G5: =(COUNTIFS('JV Readiness Plan'!$E:$E,$B5,'JV Readiness Plan'!$F:$F,G$3)) -> 0 | I5: TSA | J5: =SUM(K5:N5) -> 6 | K5: =(COUNTIFS('JV Readiness Plan'!$B:$B,$I5,'JV Readiness Plan'!$F:$F,K$3)) -> 1 | L5: =(COUNTIFS('JV Readiness Plan'!$B:$B,$I5,'JV Readiness Plan'!$F:$F,L$3)) -> 4 | M5: =(COUNTIFS('JV Readiness Plan'!$B:$B,$I5,'JV Readiness Plan'!$F:$F,M$3)) -> 1 | N5: =(COUNTIFS('JV Readiness Plan'!$B:$B,$I5,'JV Readiness Plan'!$F:$F,N$3)) -> 0
B6: Ramesh Murugesan | C6: =SUM(D6:G6) -> 13 | D6: =(COUNTIFS('JV Readiness Plan'!$E:$E,$B6,'JV Readiness Plan'!$F:$F,D$3)) -> 0 | E6: =(COUNTIFS('JV Readiness Plan'!$E:$E,$B6,'JV Readiness Plan'!$F:$F,E$3)) -> 12 | F6: =(COUNTIFS('JV Readiness Plan'!$E:$E,$B6,'JV Readiness Plan'!$F:$F,F$3)) -> 1 | G6: =(COUNTIFS('JV Readiness Plan'!$E:$E,$B6,'JV Readiness Plan'!$F:$F,G$3)) -> 0 | I6: GSA | J6: =SUM(K6:N6) -> 6 | K6: =(COUNTIFS('JV Readiness Plan'!$B:$B,$I6,'JV Readiness Plan'!$F:$F,K$3)) -> 0 | L6: =(COUNTIFS('JV Readiness Plan'!$B:$B,$I6,'JV Readiness Plan'!$F:$F,L$3)) -> 4 | M6: =(COUNTIFS('JV Readiness Plan'!$B:$B,$I6,'JV Readiness Plan'!$F:$F,M$3)) -> 2 | N6: =(COUNTIFS('JV Readiness Plan'!$B:$B,$I6,'JV Readiness Plan'!$F:$F,N$3)) -> 0
B7: Mawiyah Alqaed | C7: =SUM(D7:G7) -> 11 | D7: =(COUNTIFS('JV Readiness Plan'!$E:$E,$B7,'JV Readiness Plan'!$F:$F,D$3)) -> 0 | E7: =(COUNTIFS('JV Readiness Plan'!$E:$E,$B7,'JV Readiness Plan'!$F:$F,E$3)) -> 9 | F7: =(COUNTIFS('JV Readiness Plan'!$E:$E,$B7,'JV Readiness Plan'!$F:$F,F$3)) -> 2 | G7: =(COUNTIFS('JV Readiness Plan'!$E:$E,$B7,'JV Readiness Plan'!$F:$F,G$3)) -> 0 | I7: DoA | J7: =SUM(K7:N7) -> 3 | K7: =(COUNTIFS('JV Readiness Plan'!$B:$B,$I7,'JV Readiness Plan'!$F:$F,K$3)) -> 0 | L7: =(COUNTIFS('JV Readiness Plan'!$B:$B,$I7,'JV Readiness Plan'!$F:$F,L$3)) -> 1 | M7: =(COUNTIFS('JV Readiness Plan'!$B:$B,$I7,'JV Readiness Plan'!$F:$F,M$3)) -> 2 | N7: =(COUNTIFS('JV Readiness Plan'!$B:$B,$I7,'JV Readiness Plan'!$F:$F,N$3)) -> 0
B8: Aseel Alnafea | C8: =SUM(D8:G8) -> 8 | D8: =(COUNTIFS('JV Readiness Plan'!$E:$E,$B8,'JV Readiness Plan'!$F:$F,D$3)) -> 0 | E8: =(COUNTIFS('JV Readiness Plan'!$E:$E,$B8,'JV Readiness Plan'!$F:$F,E$3)) -> 7 | F8: =(COUNTIFS('JV Readiness Plan'!$E:$E,$B8,'JV Readiness Plan'!$F:$F,F$3)) -> 1 | G8: =(COUNTIFS('JV Readiness Plan'!$E:$E,$B8,'JV Readiness Plan'!$F:$F,G$3)) -> 0 | I8: Secondment | J8: =SUM(K8:N8) -> 4 | K8: =(COUNTIFS('JV Readiness Plan'!$B:$B,$I8,'JV Readiness Plan'!$F:$F,K$3)) -> 0 | L8: =(COUNTIFS('JV Readiness Plan'!$B:$B,$I8,'JV Readiness Plan'!$F:$F,L$3)) -> 2 | M8: =(COUNTIFS('JV Readiness Plan'!$B:$B,$I8,'JV Readiness Plan'!$F:$F,M$3)) -> 2 | N8: =(COUNTIFS('JV Readiness Plan'!$B:$B,$I8,'JV Readiness Plan'!$F:$F,N$3)) -> 0
B9: Rene Thumbran | C9: =SUM(D9:G9) -> 7 | D9: =(COUNTIFS('JV Readiness Plan'!$E:$E,$B9,'JV Readiness Plan'!$F:$F,D$3)) -> 0 | E9: =(COUNTIFS('JV Readiness Plan'!$E:$E,$B9,'JV Readiness Plan'!$F:$F,E$3)) -> 5 | F9: =(COUNTIFS('JV Readiness Plan'!$E:$E,$B9,'JV Readiness Plan'!$F:$F,F$3)) -> 2 | G9: =(COUNTIFS('JV Readiness Plan'!$E:$E,$B9,'JV Readiness Plan'!$F:$F,G$3)) -> 0 | I9: SHA documentation | J9: =SUM(K9:N9) -> 9 | K9: =(COUNTIFS('JV Readiness Plan'!$B:$B,$I9,'JV Readiness Plan'!$F:$F,K$3)) -> 0 | L9: =(COUNTIFS('JV Readiness Plan'!$B:$B,$I9,'JV Readiness Plan'!$F:$F,L$3)) -> 1 | M9: =(COUNTIFS('JV Readiness Plan'!$B:$B,$I9,'JV Readiness Plan'!$F:$F,M$3)) -> 8 | N9: =(COUNTIFS('JV Readiness Plan'!$B:$B,$I9,'JV Readiness Plan'!$F:$F,N$3)) -> 0
B10: Mohammed Al-Hamed | C10: =SUM(D10:G10) -> 6 | D10: =(COUNTIFS('JV Readiness Plan'!$E:$E,$B10,'JV Readiness Plan'!$F:$F,D$3)) -> 0 | E10: =(COUNTIFS('JV Readiness Plan'!$E:$E,$B10,'JV Readiness Plan'!$F:$F,E$3)) -> 4 | F10: =(COUNTIFS('JV Readiness Plan'!$E:$E,$B10,'JV Readiness Plan'!$F:$F,F$3)) -> 2 | G10: =(COUNTIFS('JV Readiness Plan'!$E:$E,$B10,'JV Readiness Plan'!$F:$F,G$3)) -> 0 | I10: Corporate approval | J10: =SUM(K10:N10) -> 9 | K10: =(COUNTIFS('JV Readiness Plan'!$B:$B,$I10,'JV Readiness Plan'!$F:$F,K$3)) -> 2 | L10: =(COUNTIFS('JV Readiness Plan'!$B:$B,$I10,'JV Readiness Plan'!$F:$F,L$3)) -> 5 | M10: =(COUNTIFS('JV Readiness Plan'!$B:$B,$I10,'JV Readiness Plan'!$F:$F,M$3)) -> 2 | N10: =(COUNTIFS('JV Readiness Plan'!$B:$B,$I10,'JV Readiness Plan'!$F:$F,N$3)) -> 0
B11: Faraj Al Dossary | C11: =SUM(D11:G11) -> 6 | D11: =(COUNTIFS('JV Readiness Plan'!$E:$E,$B11,'JV Readiness Plan'!$F:$F,D$3)) -> 0 | E11: =(COUNTIFS('JV Readiness Plan'!$E:$E,$B11,'JV Readiness Plan'!$F:$F,E$3)) -> 6 | F11: =(COUNTIFS('JV Readiness Plan'!$E:$E,$B11,'JV Readiness Plan'!$F:$F,F$3)) -> 0 | G11: =(COUNTIFS('JV Readiness Plan'!$E:$E,$B11,'JV Readiness Plan'!$F:$F,G$3)) -> 0 | I11: Governance | J11: =SUM(K11:N11) -> 20 | K11: =(COUNTIFS('JV Readiness Plan'!$B:$B,$I11,'JV Readiness Plan'!$F:$F,K$3)) -> 0 | L11: =(COUNTIFS('JV Readiness Plan'!$B:$B,$I11,'JV Readiness Plan'!$F:$F,L$3)) -> 18 | M11: =(COUNTIFS('JV Readiness Plan'!$B:$B,$I11,'JV Readiness Plan'!$F:$F,M$3)) -> 2 | N11: =(COUNTIFS('JV Readiness Plan'!$B:$B,$I11,'JV Readiness Plan'!$F:$F,N$3)) -> 0
B12: Omar Jabart | C12: =SUM(D12:G12) -> 6 | D12: =(COUNTIFS('JV Readiness Plan'!$E:$E,$B12,'JV Readiness Plan'!$F:$F,D$3)) -> 0 | E12: =(COUNTIFS('JV Readiness Plan'!$E:$E,$B12,'JV Readiness Plan'!$F:$F,E$3)) -> 4 | F12: =(COUNTIFS('JV Readiness Plan'!$E:$E,$B12,'JV Readiness Plan'!$F:$F,F$3)) -> 2 | G12: =(COUNTIFS('JV Readiness Plan'!$E:$E,$B12,'JV Readiness Plan'!$F:$F,G$3)) -> 0 | I12: Legal | J12: =SUM(K12:N12) -> 6 | K12: =(COUNTIFS('JV Readiness Plan'!$B:$B,$I12,'JV Readiness Plan'!$F:$F,K$3)) -> 0 | L12: =(COUNTIFS('JV Readiness Plan'!$B:$B,$I12,'JV Readiness Plan'!$F:$F,L$3)) -> 6 | M12: =(COUNTIFS('JV Readiness Plan'!$B:$B,$I12,'JV Readiness Plan'!$F:$F,M$3)) -> 0 | N12: =(COUNTIFS('JV Readiness Plan'!$B:$B,$I12,'JV Readiness Plan'!$F:$F,N$3)) -> 0
B13: Abdulrahman Abdullah Al-zahrani | C13: =SUM(D13:G13) -> 4 | D13: =(COUNTIFS('JV Readiness Plan'!$E:$E,$B13,'JV Readiness Plan'!$F:$F,D$3)) -> 0 | E13: =(COUNTIFS('JV Readiness Plan'!$E:$E,$B13,'JV Readiness Plan'!$F:$F,E$3)) -> 4 | F13: =(COUNTIFS('JV Readiness Plan'!$E:$E,$B13,'JV Readiness Plan'!$F:$F,F$3)) -> 0 | G13: =(COUNTIFS('JV Readiness Plan'!$E:$E,$B13,'JV Readiness Plan'!$F:$F,G$3)) -> 0 | I13: GR | J13: =SUM(K13:N13) -> 4 | K13: =(COUNTIFS('JV Readiness Plan'!$B:$B,$I13,'JV Readiness Plan'!$F:$F,K$3)) -> 0 | L13: =(COUNTIFS('JV Readiness Plan'!$B:$B,$I13,'JV Readiness Plan'!$F:$F,L$3)) -> 4 | M13: =(COUNTIFS('JV Readiness Plan'!$B:$B,$I13,'JV Readiness Plan'!$F:$F,M$3)) -> 0 | N13: =(COUNTIFS('JV Readiness Plan'!$B:$B,$I13,'JV Readiness Plan'!$F:$F,N$3)) -> 0
B14: Fathima Mahomed | C14: =SUM(D14:G14) -> 4 | D14: =(COUNTIFS('JV Readiness Plan'!$E:$E,$B14,'JV Readiness Plan'!$F:$F,D$3)) -> 0 | E14: =(COUNTIFS('JV Readiness Plan'!$E:$E,$B14,'JV Readiness Plan'!$F:$F,E$3)) -> 4 | F14: =(COUNTIFS('JV Readiness Plan'!$E:$E,$B14,'JV Readiness Plan'!$F:$F,F$3)) -> 0 | G14: =(COUNTIFS('JV Readiness Plan'!$E:$E,$B14,'JV Readiness Plan'!$F:$F,G$3)) -> 0 | I14: HR | J14: =SUM(K14:N14) -> 6 | K14: =(COUNTIFS('JV Readiness Plan'!$B:$B,$I14,'JV Readiness Plan'!$F:$F,K$3)) -> 0 | L14: =(COUNTIFS('JV Readiness Plan'!$B:$B,$I14,'JV Readiness Plan'!$F:$F,L$3)) -> 6 | M14: =(COUNTIFS('JV Readiness Plan'!$B:$B,$I14,'JV Readiness Plan'!$F:$F,M$3)) -> 0 | N14: =(COUNTIFS('JV Readiness Plan'!$B:$B,$I14,'JV Readiness Plan'!$F:$F,N$3)) -> 0
B15: Muddassar/Mohammed | C15: =SUM(D15:G15) -> 3 | D15: =(COUNTIFS('JV Readiness Plan'!$E:$E,$B15,'JV Readiness Plan'!$F:$F,D$3)) -> 0 | E15: =(COUNTIFS('JV Readiness Plan'!$E:$E,$B15,'JV Readiness Plan'!$F:$F,E$3)) -> 3 | F15: =(COUNTIFS('JV Readiness Plan'!$E:$E,$B15,'JV Readiness Plan'!$F:$F,F$3)) -> 0 | G15: =(COUNTIFS('JV Readiness Plan'!$E:$E,$B15,'JV Readiness Plan'!$F:$F,G$3)) -> 0 | I15: HSSE | J15: =SUM(K15:N15) -> 6 | K15: =(COUNTIFS('JV Readiness Plan'!$B:$B,$I15,'JV Readiness Plan'!$F:$F,K$3)) -> 0 | L15: =(COUNTIFS('JV Readiness Plan'!$B:$B,$I15,'JV Readiness Plan'!$F:$F,L$3)) -> 6 | M15: =(COUNTIFS('JV Readiness Plan'!$B:$B,$I15,'JV Readiness Plan'!$F:$F,M$3)) -> 0 | N15: =(COUNTIFS('JV Readiness Plan'!$B:$B,$I15,'JV Readiness Plan'!$F:$F,N$3)) -> 0
... B20: Abdullah Alzamil | C20: =SUM(D20:G20) -> 2 | D20: =(COUNTIFS('JV Readiness Plan'!$E:$E,$B20,'JV Readiness Plan'!$F:$F,D$3)) -> 0 | E20: =(COUNTIFS('JV Readiness Plan'!$E:$E,$B20,'JV Readiness Plan'!$F:$F,E$3)) -> 2 | F20: =(COUNTIFS('JV Readiness Plan'!$E:$E,$B20,'JV Readiness Plan'!$F:$F,F$3)) -> 0 | G20: =(COUNTIFS('JV Readiness Plan'!$E:$E,$B20,'JV Readiness Plan'!$F:$F,G$3)) -> 0 | I20: Facilities | J20: =SUM(K20:N20) -> 1 | K20: =(COUNTIFS('JV Readiness Plan'!$B:$B,$I20,'JV Readiness Plan'!$F:$F,K$3)) -> 0 | L20: =(COUNTIFS('JV Readiness Plan'!$B:$B,$I20,'JV Readiness Plan'!$F:$F,L$3)) -> 1 | M20: =(COUNTIFS('JV Readiness Plan'!$B:$B,$I20,'JV Readiness Plan'!$F:$F,M$3)) -> 0 | N20: =(COUNTIFS('JV Readiness Plan'!$B:$B,$I20,'JV Readiness Plan'!$F:$F,N$3)) -> 0
B21: Karim Mehboob | C21: =SUM(D21:G21) -> 2 | D21: =(COUNTIFS('JV Readiness Plan'!$E:$E,$B21,'JV Readiness Plan'!$F:$F,D$3)) -> 0 | E21: =(COUNTIFS('JV Readiness Plan'!$E:$E,$B21,'JV Readiness Plan'!$F:$F,E$3)) -> 2 | F21: =(COUNTIFS('JV Readiness Plan'!$E:$E,$B21,'JV Readiness Plan'!$F:$F,F$3)) -> 0 | G21: =(COUNTIFS('JV Readiness Plan'!$E:$E,$B21,'JV Readiness Plan'!$F:$F,G$3)) -> 0
B22: Marwan Sutan | C22: =SUM(D22:G22) -> 2 | D22: =(COUNTIFS('JV Readiness Plan'!$E:$E,$B22,'JV Readiness Plan'!$F:$F,D$3)) -> 0 | E22: =(COUNTIFS('JV Readiness Plan'!$E:$E,$B22,'JV Readiness Plan'!$F:$F,E$3)) -> 2 | F22: =(COUNTIFS('JV Readiness Plan'!$E:$E,$B22,'JV Readiness Plan'!$F:$F,F$3)) -> 0 | G22: =(COUNTIFS('JV Readiness Plan'!$E:$E,$B22,'JV Readiness Plan'!$F:$F,G$3)) -> 0
B23: Ramesh / Alex | C23: =SUM(D23:G23) -> 0 | D23: =(COUNTIFS('JV Readiness Plan'!$E:$E,$B23,'JV Readiness Plan'!$F:$F,D$3)) -> 0 | E23: =(COUNTIFS('JV Readiness Plan'!$E:$E,$B23,'JV Readiness Plan'!$F:$F,E$3)) -> 0 | F23: =(COUNTIFS('JV Readiness Plan'!$E:$E,$B23,'JV Readiness Plan'!$F:$F,F$3)) -> 0 | G23: =(COUNTIFS('JV Readiness Plan'!$E:$E,$B23,'JV Readiness Plan'!$F:$F,G$3)) -> 0
B24: Aramco | C24: =SUM(D24:G24) -> 2 | D24: =(COUNTIFS('JV Readiness Plan'!$E:$E,$B24,'JV Readiness Plan'!$F:$F,D$3)) -> 0 | E24: =(COUNTIFS('JV Readiness Plan'!$E:$E,$B24,'JV Readiness Plan'!$F:$F,E$3)) -> 2 | F24: =(COUNTIFS('JV Readiness Plan'!$E:$E,$B24,'JV Readiness Plan'!$F:$F,F$3)) -> 0 | G24: =(COUNTIFS('JV Readiness Plan'!$E:$E,$B24,'JV Readiness Plan'!$F:$F,G$3)) -> 0
B25: AshLaw | C25: =SUM(D25:G25) -> 1 | D25: =(COUNTIFS('JV Readiness Plan'!$E:$E,$B25,'JV Readiness Plan'!$F:$F,D$3)) -> 0 | E25: =(COUNTIFS('JV Readiness Plan'!$E:$E,$B25,'JV Readiness Plan'!$F:$F,E$3)) -> 1 | F25: =(COUNTIFS('JV Readiness Plan'!$E:$E,$B25,'JV Readiness Plan'!$F:$F,F$3)) -> 0 | G25: =(COUNTIFS('JV Readiness Plan'!$E:$E,$B25,'JV Readiness Plan'!$F:$F,G$3)) -> 0
B26: Raud Alsuwailem | C26: =SUM(D26:G26) -> 1 | D26: =(COUNTIFS('JV Readiness Plan'!$E:$E,$B26,'JV Readiness Plan'!$F:$F,D$3)) -> 0 | E26: =(COUNTIFS('JV Readiness Plan'!$E:$E,$B26,'JV Readiness Plan'!$F:$F,E$3)) -> 1 | F26: =(COUNTIFS('JV Readiness Plan'!$E:$E,$B26,'JV Readiness Plan'!$F:$F,F$3)) -> 0 | G26: =(COUNTIFS('JV Readiness Plan'!$E:$E,$B26,'JV Readiness Plan'!$F:$F,G$3)) -> 0
B27: Governance Dept | C27: =SUM(D27:G27) -> 1 | D27: =(COUNTIFS('JV Readiness Plan'!$E:$E,$B27,'JV Readiness Plan'!$F:$F,D$3)) -> 0 | E27: =(COUNTIFS('JV Readiness Plan'!$E:$E,$B27,'JV Readiness Plan'!$F:$F,E$3)) -> 1 | F27: =(COUNTIFS('JV Readiness Plan'!$E:$E,$B27,'JV Readiness Plan'!$F:$F,F$3)) -> 0 | G27: =(COUNTIFS('JV Readiness Plan'!$E:$E,$B27,'JV Readiness Plan'!$F:$F,G$3)) -> 0
B28: Raoof Madathil | C28: =SUM(D28:G28) -> 1 | D28: =(COUNTIFS('JV Readiness Plan'!$E:$E,$B28,'JV Readiness Plan'!$F:$F,D$3)) -> 0 | E28: =(COUNTIFS('JV Readiness Plan'!$E:$E,$B28,'JV Readiness Plan'!$F:$F,E$3)) -> 1 | F28: =(COUNTIFS('JV Readiness Plan'!$E:$E,$B28,'JV Readiness Plan'!$F:$F,F$3)) -> 0 | G28: =(COUNTIFS('JV Readiness Plan'!$E:$E,$B28,'JV Readiness Plan'!$F:$F,G$3)) -> 0

Sheet JV Readiness Plan
A1: PROJECT CRYSTAL - JV DAY-1 READINESS PLAN | H1: Day-1 target date | I1: =MAX(I4:I133) -> 46265
A3: Workstream | B3: Category | C3: Requirement | D3: Action | E3: Owner | F3: Status | G3: Start date | H3: Duration | I3: End date | J3: Target Completion (%) | K3: Actual Completion (%)
B4: Budget and Business Plan | G4: =MIN(G5:G13) -> 46054 | H4: =I4-G4 -> 58 | I4: =MAX(I5:I13) -> 46112
A5: SHA | B5: Budget and BP | C5: Budget & BP Roles & Data Sources | D5: Clarify roles and responsibilities across Maaden finance and technical teams. Define who provides what, sources of information, and internal points of contact for each workstream. | E5: Hassen Moolla | F5: Completed | G5: 46054 | H5: 14 | I5: =G5+H5 -> 46068 | J5: =IFERROR(MAX(0,MIN(1,(TODAY()-G5)/(I5-G5))),"") -> 1 | K5: 1
A6: SHA | B6: Budget and BP | C6: Budget and BP Inputs & Assumptions | D6: Identify the full list of inputs and assumptions required to build the model. Define sources and providers for each item, and set deadlines for delivery. | E6: Hassen Moolla | F6: On-track | G6: =I5 -> 46068 | H6: 18 | I6: =G6+H6 -> 46086 | J6: =IFERROR(MAX(0,MIN(1,(TODAY()-G6)/(I6-G6))),"") -> 0.83333333 | K6: 0.8
A7: SHA | B7: Budget and BP | C7: 5-Year Exploration Plan | D7: Develop 5-year Exploration Plan (2026-2030) | E7: Owen Hatton | F7: On-track | G7: =I5 -> 46068 | H7: 18 | I7: =G7+H7 -> 46086 | J7: =IFERROR(MAX(0,MIN(1,(TODAY()-G7)/(I7-G7))),"") -> 0.83333333 | K7: 0.8
A8: SHA | B8: Budget and BP | C8: JV Day-1 Org Chart | D8: Finalize the Day-1 organization structure (confirm minimal technical staff requirements, including HSSE) | E8: Mohammed Al-Hamed | F8: On-track | G8: 46071 | H8: 14 | I8: =G8+H8 -> 46085 | J8: =IFERROR(MAX(0,MIN(1,(TODAY()-G8)/(I8-G8))),"") -> 0.85714286 | K8: 0.5
A9: SHA | B9: Budget and BP | C9: Build Draft BP Model | D9: Construct the financial and operational model based on the defined inputs, assumptions, and agreed structure. Ensure formulas are robust and the model is auditable. | E9: Hassen Moolla | F9: On-track | G9: =I7 -> 46086 | H9: 7 | I9: =G9+H9 -> 46093 | J9: =IFERROR(MAX(0,MIN(1,(TODAY()-G9)/(I9-G9))),"") -> 0 | K9: 0
A10: SHA | B10: Budget and BP | C10: Validate BP with Key Maaden Stakeholders | D10: Present the draft model and BP outputs to key Maaden stakeholders (technical and finance) for review. Incorporate feedback and resolve any open items. | E10: Hassen Moolla | F10: Not Started | G10: =I9 -> 46093 | H10: 3 | I10: =G10+H10 -> 46096 | J10: =IFERROR(MAX(0,MIN(1,(TODAY()-G10)/(I10-G10))),"") -> 0 | K10: 0
A11: SHA | B11: Budget and BP | C11: Package BP into Final Deliverable | D11: Define format/templates and develop final deliverables | E11: Hassen Moolla | F11: Not Started | G11: =I10 -> 46096 | H11: 7 | I11: =G11+H11 -> 46103 | J11: =IFERROR(MAX(0,MIN(1,(TODAY()-G11)/(I11-G11))),"") -> 0 | K11: 0
A12: SHA | B12: Budget and BP | C12: BP Final Deliverable validation | D12: Validate final deliverables | E12: Mohammed Al-Hamed | F12: Not Started | G12: =I11 -> 46103 | H12: 2 | I12: =G12+H12 -> 46105 | J12: =IFERROR(MAX(0,MIN(1,(TODAY()-G12)/(I12-G12))),"") -> 0 | K12: 0
A13: SHA | B13: Budget and BP | C13: Aramco Feedback on BP & Update | D13: Share the finalized BP with Aramco for review. Collect feedback, incorporate agreed changes, and lock the final version for approval | E13: Mohammed Al-Hamed | F13: Not Started | G13: =I12 -> 46105 | H13: 7 | I13: =G13+H13 -> 46112 | J13: =IFERROR(MAX(0,MIN(1,(TODAY()-G13)/(I13-G13))),"") -> 0 | K13: 0
B14: TSA | G14: =MIN(G15:G20) -> 46054 | H14: =I14-G14 -> 66 | I14: =MAX(I15:I20) -> 46120
A15: SHA | B15: TSA | C15: TSA Technical Services Catalogue | D15: Develop the catalogue of technical services to be provided by Maaden to the JV under the TSA, identify what services are to be provided by 3d parties | E15: Owen Hatton | F15: Completed | G15: 46054 | H15: 11 | I15: =G15+H15 -> 46065 | J15: =IFERROR(MAX(0,MIN(1,(TODAY()-G15)/(I15-G15))),"") -> 1 | K15: 1
A16: SHA | B16: TSA | C16: TSA Charge-out Rate Methodology | D16: Define the pricing methodology: establish the approach and basis for pricing each category of services (e.g., cost-plus, market benchmark, fixed fee) | E16: Hassen Moolla | F16: On-track | G16: =I15 -> 46065 | H16: 24 | I16: =G16+H16 -> 46089 | J16: =IFERROR(MAX(0,MIN(1,(TODAY()-G16)/(I16-G16))),"") -> 0.75 | K16: 1
A17: SHA | B17: TSA | C17: TSA Charge-out Rates Determination | D17: Apply the agreed pricing methodology to determine the applicable rates for each service in the catalogue | E17: Hassen Moolla | F17: Not Started | G17: =I16 -> 46089 | H17: 7 | I17: =G17+H17 -> 46096 | J17: =IFERROR(MAX(0,MIN(1,(TODAY()-G17)/(I17-G17))),"") -> 0 | K17: 0
A18: SHA | B18: TSA | C18: TSA Governance structure | D18: Define TSA governance structure and process: how TSA services are requested, approved, monitored, billed, paid, accounted (TSA management process) | E18: Muddassar | F18: Not Started | G18: 46085 | H18: 14 | I18: =G18+H18 -> 46099 | J18: =IFERROR(MAX(0,MIN(1,(TODAY()-G18)/(I18-G18))),"") -> 0 | K18: 0
A19: SHA | B19: TSA | C19: TSA Legal framework | D19: Finalize the TSA legal framework: draft and agree on the legal terms and conditions governing the provision of services, including scope, performance standards, liability, and termination provisions | E19: Aseel Alnafea | F19: Not Started | G19: =I18 -> 46099 | H19: 14 | I19: =G19+H19 -> 46113 | J19: =IFERROR(MAX(0,MIN(1,(TODAY()-G19)/(I19-G19))),"") -> 0 | K19: 0
A20: SHA | B20: TSA | C20: Aramco Feedback on TSA & Update | D20: Share the finalized TSA version with Aramco for review. Collect feedback, incorporate agreed changes, and lock the final version for approval. | E20: Muddassar Khan | F20: Not Started | G20: =I19 -> 46113 | H20: 7 | I20: =G20+H20 -> 46120 | J20: =IFERROR(MAX(0,MIN(1,(TODAY()-G20)/(I20-G20))),"") -> 0 | K20: 0
B21: GSA | G21: =MIN(G22:G27) -> 46054 | H21: =I21-G21 -> 66 | I21: =MAX(I22:I27) -> 46120
A22: SHA | B22: GSA | C22: GSA Catalogue of services | D22: Develop the catalogue of services to be provided by Maaden to the JV under the GSA | E22: Hassen Moolla | F22: On-track | G22: 46054 | H22: 35 | I22: =G22+H22 -> 46089 | J22: =IFERROR(MAX(0,MIN(1,(TODAY()-G22)/(I22-G22))),"") -> 0.82857143 | K22: 0.75
A23: SHA | B23: GSA | C23: GSA Charge-out Rate Methodology | D23: Define the pricing methodology: establish the approach and basis for pricing each category of services (e.g., cost-plus, market benchmark, fixed fee) | E23: Hassen Moolla | F23: On-track | G23: 46069 | H23: 24 | I23: =G23+H23 -> 46093 | J23: =IFERROR(MAX(0,MIN(1,(TODAY()-G23)/(I23-G23))),"") -> 0.58333333 | K23: 1
A24: SHA | B24: GSA | C24: GSA Charge-out Rates Determination | D24: Apply the agreed pricing methodology to determine the applicable rates for each service in the catalogue | E24: Hassen Moolla | F24: Not Started | G24: =I23 -> 46093 | H24: 7 | I24: =G24+H24 -> 46100 | J24: =IFERROR(MAX(0,MIN(1,(TODAY()-G24)/(I24-G24))),"") -> 0 | K24: 0
A25: SHA | B25: GSA | C25: GSA Governance structure | D25: Define GSA governance structure and process : how GSA services are requested, approved, monitored, billed, paid, accounted (GSA management process) | E25: Muddassar | F25: Not Started | G25: 46085 | H25: 14 | I25: =G25+H25 -> 46099 | J25: =IFERROR(MAX(0,MIN(1,(TODAY()-G25)/(I25-G25))),"") -> 0 | K25: 0
A26: SHA | B26: GSA | C26: GSA Legal framework | D26: Finalize the GSA legal framework: draft and agree on the legal terms and conditions governing the provision of services, including scope, performance standards, liability, and termination provisions | E26: Aseel Alnafea | F26: Not Started | G26: =I25 -> 46099 | H26: 14 | I26: =G26+H26 -> 46113 | J26: =IFERROR(MAX(0,MIN(1,(TODAY()-G26)/(I26-G26))),"") -> 0 | K26: 0
A27: SHA | B27: GSA | C27: Aramco Feedback on GSA & Update | D27: Share the finalized TSA version with Aramco for review. Collect feedback, incorporate agreed changes, and lock the final version for approval | E27: Muddassar Khan | F27: Not Started | G27: =I26 -> 46113 | H27: 7 | I27: =G27+H27 -> 46120 | J27: =IFERROR(MAX(0,MIN(1,(TODAY()-G27)/(I27-G27))),"") -> 0 | K27: 0
B28: DoA | G28: =MIN(G29:G31) -> 46068 | H28: =I28-G28 -> 37 | I28: =MAX(I29:I31) -> 46105
A29: SHA | B29: DoA | C29: Shareholders DoAs reference | D29: Obtain reference governance framework, obtain Maaden's existing Authority Matrix and Aramco's governance frameworks as benchmarks for the JV | E29: Mawiyah Alqaed | F29: On-track | G29: 46077 | H29: 9 | I29: =G29+H29 -> 46086 | J29: =IFERROR(MAX(0,MIN(1,(TODAY()-G29)/(I29-G29))),"") -> 0.66666667 | K29: 0.8
A30: SHA | B30: DoA | C30: Complete Design of DoA (Shedule 15) | D30: Design the multi-tiered financial approval matrix (incl governance and internal controls) : define approval tiers below Board thresholds across CAPEX, OPEX, contracts, procurement, HR, litigation, treasury, and asset management, aligned with SHA | E30: Omar Jabart | F30: On-track | G30: 46068 | H30: 30 | I30: =G30+H30 -> 46098 | J30: =IFERROR(MAX(0,MIN(1,(TODAY()-G30)/(I30-G30))),"") -> 0.5 | K30: 0.4
A31: SHA | B31: DoA | C31: Aramco Feedback on DoA & Update | D31: Share the finalized DoA version with Aramco for review. Collect feedback, incorporate agreed changes, and lock the final version for approval | E31: Muddassar/Mohammed | F31: Not Started | G31: =I30 -> 46098 | H31: 7 | I31: =G31+H31 -> 46105 | J31: =IFERROR(MAX(0,MIN(1,(TODAY()-G31)/(I31-G31))),"") -> 0 | K31: 0
B32: Secondment | G32: =MIN(G33:G36) -> 46054 | H32: =I32-G32 -> 62 | I32: =MAX(I33:I36) -> 46116
A33: SHA | B33: Secondment | C33: Secondment framework | D33: Develop secondment framework agreement (duration, cost basis, reporting lines, benefits) | E33: Rene Thumbran | F33: On-track | G33: 46054 | H33: 40 | I33: =G33+H33 -> 46094 | J33: =IFERROR(MAX(0,MIN(1,(TODAY()-G33)/(I33-G33))),"") -> 0.725 | K33: 0.6
A34: SHA | B34: Secondment | C34: Secondment Agreement Allocation Methodology | D34: Define cost allocation methodology and determine cost rates for secondees | E34: Rene Thumbran | F34: On-track | G34: 46055 | H34: 40 | I34: =G34+H34 -> 46095 | J34: =IFERROR(MAX(0,MIN(1,(TODAY()-G34)/(I34-G34))),"") -> 0.7 | K34: 0.6
A35: SHA | B35: Secondment | C35: JV Secondment Agreement draft | D35: Draft JV secondment agreement | E35: Aseel Alnafea | F35: Not Started | G35: =I34 -> 46095 | H35: 14 | I35: =G35+H35 -> 46109 | J35: =IFERROR(MAX(0,MIN(1,(TODAY()-G35)/(I35-G35))),"") -> 0 | K35: 0
A36: SHA | B36: Secondment | C36: Aramco Feedback on Secondment Agreement & Update | D36: Share the finalized Secondment Agreement with Aramco for review. Collect feedback, incorporate agreed changes, and lock the final version for approval | E36: Muddassar/Mohammed | F36: Not Started | G36: =I35 -> 46109 | H36: 7 | I36: =G36+H36 -> 46116 | J36: =IFERROR(MAX(0,MIN(1,(TODAY()-G36)/(I36-G36))),"") -> 0 | K36: 0
B37: SHA documentation | G37: =MIN(G38:G46) -> 46072 | H37: =I37-G37 -> 62 | I37: =MAX(I38:I46) -> 46134
A38: SHA | B38: SHA documentation | C38: SHA Sch.10 Guarantee for Permitted Transfers | D38: Agree Form of Guarantee for Permitted Transfers (Schedule 10) | E38: Muddassar Khan | F38: On-track | G38: 46072 | H38: 20 | I38: =G38+H38 -> 46092 | J38: =IFERROR(MAX(0,MIN(1,(TODAY()-G38)/(I38-G38))),"") -> 0.55 | K38: 0.25
A39: SHA | B39: SHA documentation | C39: SHA Sch.11 Form of the Agreement | D39: Finalize Form of Shareholder Services Agreement (Schedule 11) | E39: Muddassar Khan | F39: On-track | G39: 46072 | H39: 20 | I39: =G39+H39 -> 46092 | J39: =IFERROR(MAX(0,MIN(1,(TODAY()-G39)/(I39-G39))),"") -> 0.55 | K39: 0.25
A40: SHA | B40: SHA documentation | C40: SHA Sch.16 Economical assumptions | D40: Agree economic assumptions for technical studies (Schedule 16) - confirm applicability for Hard-Rock Exploration phase | E40: Muddassar Khan | F40: On-track | G40: 46072 | H40: 20 | I40: =G40+H40 -> 46092 | J40: =IFERROR(MAX(0,MIN(1,(TODAY()-G40)/(I40-G40))),"") -> 0.55 | K40: 0.25
A41: SHA | B41: SHA documentation | C41: SHA Sch.13 Competing business disclosure | D41: Complete existing competing businesses disclosure (Schedule 13) (action also required for aramco) | E41: Aseel Alnafea | F41: On-track | G41: 46077 | H41: 14 | I41: =G41+H41 -> 46091 | J41: =IFERROR(MAX(0,MIN(1,(TODAY()-G41)/(I41-G41))),"") -> 0.42857143 | K41: 0.25
A42: SHA | B42: SHA documentation | C42: SHA Sch.14 Funding Notices | D42: Develop Form of Funding Notices, and standard Funding Request Notice template (Schedule 14) | E42: Hassen Moolla | F42: On-track | G42: 46072 | H42: 14 | I42: =G42+H42 -> 46086 | J42: =IFERROR(MAX(0,MIN(1,(TODAY()-G42)/(I42-G42))),"") -> 0.78571429 | K42: 0.25
A43: SHA | B43: SHA documentation | C43: SHA Sch.2 Area of Interest and Transition Zone | D43: Provide all Area of Interest and Transition Zone maps and coordinates (Schedule 2) | E43: Mohammed Al-Hamed | F43: On-track | G43: 46072 | H43: 14 | I43: =G43+H43 -> 46086 | J43: =IFERROR(MAX(0,MIN(1,(TODAY()-G43)/(I43-G43))),"") -> 0.78571429 | K43: 0.25
A44: SHA | B44: SHA documentation | C44: Exploration License Assignment Agreeement | D44: Finalize Exploration License Assignment Agreeement | E44: Muddassar Khan | F44: On-track | G44: 46072 | H44: 42 | I44: =G44+H44 -> 46114 | J44: =IFERROR(MAX(0,MIN(1,(TODAY()-G44)/(I44-G44))),"") -> 0.26190476 | K44: 0.25
A45: SHA | B45: SHA documentation | C45: Exploration Services Agreement | D45: Finalize Exploration Services Agreement | E45: Muddassar Khan | F45: On-track | G45: 46072 | H45: 42 | I45: =G45+H45 -> 46114 | J45: =IFERROR(MAX(0,MIN(1,(TODAY()-G45)/(I45-G45))),"") -> 0.26190476 | K45: 0.25
A46: SHA | B46: SHA documentation | C46: Aramco Feedback on SHA pack & Update | D46: Share the final SHA documentation with Aramco for review. Collect feedback, incorporate agreed changes, and lock the final version for approval | E46: Muddassar/Mohammed | F46: Not Started | G46: =MAX(I38:I45) -> 46114 | H46: 20 | I46: =G46+H46 -> 46134 | J46: =IFERROR(MAX(0,MIN(1,(TODAY()-G46)/(I46-G46))),"") -> 0 | K46: 0
B47: Corporate approval | G47: =MIN(G48:G56) -> 46061 | H47: =I47-G47 -> 100 | I47: =MAX(I48:I56) -> 46161
A48: SHA | B48: Corporate approval | C48: Maaden IC | D48: Prepare material and obtain approval at Maaden Investment Committee meeting | E48: Muddassar Khan | F48: Completed | G48: 46061 | H48: 1 | I48: =G48+H48 -> 46062 | J48: =IFERROR(MAX(0,MIN(1,(TODAY()-G48)/(I48-G48))),"") -> 1 | K48: 1
A49: SHA | B49: Corporate approval | C49: Maaden ExCom | D49: Prepare material and obtain approval at Maaden Excom meeting (Feb 17) | E49: Muddassar Khan | F49: Completed | G49: 46070 | H49: 1 | I49: =G49+H49 -> 46071 | J49: =IFERROR(MAX(0,MIN(1,(TODAY()-G49)/(I49-G49))),"") -> 1 | K49: 1
A50: SHA | B50: Corporate approval | C50: Maaden BoD | D50: Prepare material and obtain approval at BoD meeting (Mar 5) | E50: Muddassar Khan | F50: Not Started | G50: 46086 | H50: 1 | I50: =G50+H50 -> 46087 | J50: =IFERROR(MAX(0,MIN(1,(TODAY()-G50)/(I50-G50))),"") -> 0 | K50: 0
A51: SHA | B51: Corporate approval | C51: 365-Day Implementation Plan Draft | D51: Draft 365 Day Implementation Plan | E51: Muddassar Khan | F51: On-track | G51: 46076 | H51: 14 | I51: =G51+H51 -> 46090 | J51: =IFERROR(MAX(0,MIN(1,(TODAY()-G51)/(I51-G51))),"") -> 0.5 | K51: 0.2
A52: SHA | B52: Corporate approval | C52: 365-Day Implementation Plan (Final) | D52: Share the finalized Plan with Aramco for review. Collect feedback, incorporate agreed changes, and lock the final version for approval | E52: Muddassar Khan | F52: Not Started | G52: =I51 -> 46090 | H52: 7 | I52: =G52+H52 -> 46097 | J52: =IFERROR(MAX(0,MIN(1,(TODAY()-G52)/(I52-G52))),"") -> 0 | K52: 0
A53: SHA | B53: Corporate approval | C53: 5-year Implementation Plan Draft | D53: Draft JV Long-term Implementation Plan (key milestones) | E53: Muddassar Khan | F53: On-track | G53: 46076 | H53: 14 | I53: =G53+H53 -> 46090 | J53: =IFERROR(MAX(0,MIN(1,(TODAY()-G53)/(I53-G53))),"") -> 0.5 | K53: 0.2
A54: SHA | B54: Corporate approval | C54: 5-year Implementation Plan (Final) | D54: Share the finalized Plan with Aramco for review. Collect feedback, incorporate agreed changes, and lock the final version for approval | E54: Muddassar Khan | F54: Not Started | G54: =I53 -> 46090 | H54: 7 | I54: =G54+H54 -> 46097 | J54: =IFERROR(MAX(0,MIN(1,(TODAY()-G54)/(I54-G54))),"") -> 0 | K54: 0
A55: SHA | B55: Corporate approval | C55: Board of Directors Aramco | D55: Obtain approval at BoD meeting (mid-May) | E55: Aramco | F55: Not Started | G55: 46155 | H55: 1 | I55: =G55+H55 -> 46156 | J55: =IFERROR(MAX(0,MIN(1,(TODAY()-G55)/(I55-G55))),"") -> 0 | K55: 0
A56: SHA | B56: Corporate approval | C56: SHA signed by both Shareholders | D56: Sign Shareholder Agreement | E56: Maaden and Aramco CEOs | F56: Not Started | G56: =I55 -> 46156 | H56: 5 | I56: =G56+H56 -> 46161 | J56: =IFERROR(MAX(0,MIN(1,(TODAY()-G56)/(I56-G56))),"") -> 0 | K56: 0
B57: Entity Formation | G57: =MIN(G58:G76) -> 46082 | H57: =I57-G57 -> 148 | I57: =MAX(I58:I76) -> 46230
A58: Entity Formation | B58: Governance | C58: Power of Attorney (PoA) | D58: Issue legalized power of attorney authorizing Kingdom representatives before MOC and SBC (action also required for Aramco) | E58: Omar Jabart | F58: On-track | G58: 46082 | H58: 14 | I58: =G58+H58 -> 46096 | J58: =IFERROR(MAX(0,MIN(1,(TODAY()-G58)/(I58-G58))),"") -> 0.071428571 | K58: 0
A59: Entity Formation | B59: Governance | C59: Trade name reservation | D59: Submit reservation of Trade name with Saudi Business Center (SBC), and obtain name approval from MOC | E59: AshLaw | F59: Not Started | G59: =I58 -> 46096 | H59: 7 | I59: =G59+H59 -> 46103 | J59: =IFERROR(MAX(0,MIN(1,(TODAY()-G59)/(I59-G59))),"") -> 0 | K59: 0
A60: Entity Formation | B60: Governance | C60: Constitutional documents | D60: Gather constitutional documents and Financial Statements (e.g., certificate of incorporation and articles (or equivalent) and audited financial statements of each Shareholder | E60: Mawiyah Alqaed | F60: Not Started | G60: 46096 | H60: 14 | I60: =G60+H60 -> 46110 | J60: =IFERROR(MAX(0,MIN(1,(TODAY()-G60)/(I60-G60))),"") -> 0 | K60: 0
A61: Entity Formation | B61: Governance | C61: Initial Board remuneration | D61: Define initial remuneration for Board Memebrs (action also required for Aramco) | E61: Mawiyah Alqaed | F61: On-track | G61: 46082 | H61: 14 | I61: =G61+H61 -> 46096 | J61: =IFERROR(MAX(0,MIN(1,(TODAY()-G61)/(I61-G61))),"") -> 0.071428571 | K61: 0
A62: Entity Formation | B62: Governance | C62: Board members nomination | D62: Both shareholders nominate board members | E62: Maaden and Aramco CEOs | F62: Not Started | G62: 46114 | H62: 7 | I62: =G62+H62 -> 46121 | J62: =IFERROR(MAX(0,MIN(1,(TODAY()-G62)/(I62-G62))),"") -> 0 | K62: 0
A63: Entity Formation | B63: Governance | C63: Board members’ and GM information | D63: Gather - from each board member and GM - a copy of passport/ID and contact information for MoC (action also required for Aramco) | E63: Mawiyah Alqaed | F63: Not Started | G63: 46114 | H63: 14 | I63: =G63+H63 -> 46128 | J63: =IFERROR(MAX(0,MIN(1,(TODAY()-G63)/(I63-G63))),"") -> 0 | K63: 0
A64: Entity Formation | B64: Governance | C64: Details of the ultimate beneficiary(ies) for MOC | D64: Gather information of the ultimate beneficiaries for Ministry of Commerce | E64: Mawiyah Alqaed | F64: Not Started | G64: 46142 | H64: 14 | I64: =G64+H64 -> 46156 | J64: =IFERROR(MAX(0,MIN(1,(TODAY()-G64)/(I64-G64))),"") -> 0 | K64: 0
A65: Entity Formation | B65: Governance | C65: Board members/GM appointment consent | D65: Board members and GM to approve their appointment - completed via Absher digital system (action also required for Aramco) | E65: Mawiyah Alqaed | F65: Not Started | G65: 46114 | H65: 14 | I65: =G65+H65 -> 46128 | J65: =IFERROR(MAX(0,MIN(1,(TODAY()-G65)/(I65-G65))),"") -> 0 | K65: 0
A66: Entity Formation | B66: Legal | C66: GAC no-notification application form | D66: Prepare GAC no-notification application form to be submitted to the GAC | E66: Aseel Alnafea | F66: Not Started | G66: 46127 | H66: 7 | I66: =G66+H66 -> 46134 | J66: =IFERROR(MAX(0,MIN(1,(TODAY()-G66)/(I66-G66))),"") -> 0 | K66: 0
A67: Entity Formation | B67: Legal | C67: GAC no-notification economic report | D67: Submit GAC no-notification economic report | E67: Aseel Alnafea | F67: Not Started | G67: 46127 | H67: 7 | I67: =G67+H67 -> 46134 | J67: =IFERROR(MAX(0,MIN(1,(TODAY()-G67)/(I67-G67))),"") -> 0 | K67: 0
A68: Entity Formation | B68: Legal | C68: GAC approval | D68: Apply for and receive all required antitrust approvals (including GAC confirmation of non-applicability) | E68: Aseel Alnafea | F68: Not Started | G68: =I56 -> 46161 | H68: 60 | I68: =G68+H68 -> 46221 | J68: =IFERROR(MAX(0,MIN(1,(TODAY()-G68)/(I68-G68))),"") -> 0 | K68: 0
A69: Entity Formation | B69: Governance | C69: Board appointment Shareholders resolutions | D69: Each Shareholder formally approves the appointment of their nominated Directors (action also required for Aramco) | E69: Mawiyah Alqaed | F69: Not Started | G69: 46114 | H69: 14 | I69: =G69+H69 -> 46128 | J69: =IFERROR(MAX(0,MIN(1,(TODAY()-G69)/(I69-G69))),"") -> 0 | K69: 0
A70: Entity Formation | B70: Governance | C70: AoA drafting | D70: Draft AoA incorporating SHA terms and get shareholders approval | E70: Omar Jabart | F70: Not Started | G70: 46127 | H70: 21 | I70: =G70+H70 -> 46148 | J70: =IFERROR(MAX(0,MIN(1,(TODAY()-G70)/(I70-G70))),"") -> 0 | K70: 0
A71: Entity Formation | B71: Governance | C71: AoA approval | D71: Submit AoA through SBC Portal (MOC) for MOC approval | E71: Omar Jabart | F71: Not Started | G71: =I70 -> 46148 | H71: 21 | I71: =G71+H71 -> 46169 | J71: =IFERROR(MAX(0,MIN(1,(TODAY()-G71)/(I71-G71))),"") -> 0 | K71: 0
A72: Entity Formation | B72: Legal | C72: AoA signing | D72: Sign AoA before MOC/SBC official (via SBC portal) (with participation of Aramco) | E72: Aseel Alnafea | F72: Not Started | G72: =I68 -> 46221 | H72: 1 | I72: =G72+H72 -> 46222 | J72: =IFERROR(MAX(0,MIN(1,(TODAY()-G72)/(I72-G72))),"") -> 0 | K72: 0
A73: Entity Formation | B73: Governance | C73: AoA issuing | D73: Complete payment of the MOC application and publication fees, Deliver Articles of Association issued electronically via the SBC portal | E73: Mawiyah Alqaed | F73: Not Started | G73: =I72 -> 46222 | H73: 2 | I73: =G73+H73 -> 46224 | J73: =IFERROR(MAX(0,MIN(1,(TODAY()-G73)/(I73-G73))),"") -> 0 | K73: 0
A74: Entity Formation | B74: Governance | C74: Maaden Board Members Registration with MOC | D74: Formally register all Maaden directors with MOC | E74: Omar Jabart | F74: Not Started | G74: =I73 -> 46224 | H74: 3 | I74: =G74+H74 -> 46227 | J74: =IFERROR(MAX(0,MIN(1,(TODAY()-G74)/(I74-G74))),"") -> 0 | K74: 0
A75: Entity Formation | B75: Governance | C75: Aramco Board Members Registration with MOC | D75: Formally register all Aramco directors with MOC | E75: Aramco | F75: Not Started | G75: =I73 -> 46224 | H75: 3 | I75: =G75+H75 -> 46227 | J75: =IFERROR(MAX(0,MIN(1,(TODAY()-G75)/(I75-G75))),"") -> 0 | K75: 0
A76: Entity Formation | B76: Governance | C76: Commercial Registration (CR) | D76: Obtain CR from Ministry of Commerce | E76: Omar Jabart | F76: Not Started | G76: =I74 -> 46227 | H76: 3 | I76: =G76+H76 -> 46230 | J76: =IFERROR(MAX(0,MIN(1,(TODAY()-G76)/(I76-G76))),"") -> 0 | K76: 0
B77: Post-formation registration | G77: =MIN(G78:G86) -> 46230 | H77: =I77-G77 -> 14 | I77: =MAX(I78:I86) -> 46244
A78: Post-formation registration | B78: GR | C78: Chamber of Commerce registration | D78: Register with local Chamber of Commerce | E78: Abdulrahman Abdullah Al-zahrani | F78: Not Started | G78: =I76 -> 46230 | H78: 7 | I78: =G78+H78 -> 46237 | J78: =IFERROR(MAX(0,MIN(1,(TODAY()-G78)/(I78-G78))),"") -> 0 | K78: 0
A79: Post-formation registration | B79: Legal | C79: ZAKAT, TAX and Customs registration | D79: Register with the ZAKAT, Tax and Customs Authority | E79: Abdullah Alzamil | F79: Not Started | G79: =I76 -> 46230 | H79: 7 | I79: =G79+H79 -> 46237 | J79: =IFERROR(MAX(0,MIN(1,(TODAY()-G79)/(I79-G79))),"") -> 0 | K79: 0
A80: Post-formation registration | B80: Legal | C80: VAT registration | D80: Register for VAT with ZATCA | E80: Abdullah Alzamil | F80: Not Started | G80: =I76 -> 46230 | H80: 14 | I80: =G80+H80 -> 46244 | J80: =IFERROR(MAX(0,MIN(1,(TODAY()-G80)/(I80-G80))),"") -> 0 | K80: 0
A81: Post-formation registration | B81: GR | C81: GOSI registration | D81: Register with General Organization for Social Insurance (GOSI) | E81: Abdulrahman Abdullah Al-zahrani | F81: Not Started | G81: =I76 -> 46230 | H81: 7 | I81: =G81+H81 -> 46237 | J81: =IFERROR(MAX(0,MIN(1,(TODAY()-G81)/(I81-G81))),"") -> 0 | K81: 0
A82: Post-formation registration | B82: HR | C82: MHRSD registration | D82: Register with Ministry of Human Resources (MHRSD) | E82: Rene Thumbran | F82: Not Started | G82: =I76 -> 46230 | H82: 7 | I82: =G82+H82 -> 46237 | J82: =IFERROR(MAX(0,MIN(1,(TODAY()-G82)/(I82-G82))),"") -> 0 | K82: 0
A83: Post-formation registration | B83: GR | C83: Saudi Post Registration | D83: Registration with the Saudi Post Office | E83: Abdulrahman Abdullah Al-zahrani | F83: Not Started | G83: =I76 -> 46230 | H83: 7 | I83: =G83+H83 -> 46237 | J83: =IFERROR(MAX(0,MIN(1,(TODAY()-G83)/(I83-G83))),"") -> 0 | K83: 0
A84: Post-formation registration | B84: GR | C84: Municipality License | D84: Obtain a municipality License from Ministry of Municipal and Rural Affairs | E84: Abdulrahman Abdullah Al-zahrani | F84: Not Started | G84: =I76 -> 46230 | H84: 14 | I84: =G84+H84 -> 46244 | J84: =IFERROR(MAX(0,MIN(1,(TODAY()-G84)/(I84-G84))),"") -> 0 | K84: 0
A85: Post-formation registration | B85: HR | C85: Nitaqat classification | D85: Obtain initial Saudization classification | E85: Rene Thumbran | F85: Not Started | G85: =I76 -> 46230 | H85: 14 | I85: =G85+H85 -> 46244 | J85: =IFERROR(MAX(0,MIN(1,(TODAY()-G85)/(I85-G85))),"") -> 0 | K85: 0
A86: Post-formation registration | B86: HSSE | C86: Civil Defence Certificate | D86: Obtain a Civil Defence Certificate, as necessary | E86: Faraj Al Dossary | F86: Not Started | G86: =I76 -> 46230 | H86: 14 | I86: =G86+H86 -> 46244 | J86: =IFERROR(MAX(0,MIN(1,(TODAY()-G86)/(I86-G86))),"") -> 0 | K86: 0
B87: Corporate Governance Setup | G87: =MIN(G88:G92) -> 46161 | H87: =I87-G87 -> 97 | I87: =MAX(I88:I92) -> 46258
A88: Corporate Governance Setup | B88: Governance | C88: BoD Charter | D88: Develop BoD Charter (incl. board composition, committees, authority matrices, voting & veto rights, exec management governance, performance assessment) | E88: Mawiyah Alqaed | F88: Not Started | G88: =I56 -> 46161 | H88: 21 | I88: =G88+H88 -> 46182 | J88: =IFERROR(MAX(0,MIN(1,(TODAY()-G88)/(I88-G88))),"") -> 0 | K88: 0
A89: Corporate Governance Setup | B89: Governance | C89: Board of Directors on-boarding | D89: Prepare on-boarding documentation for JV Board of Directors | E89: Raud Alsuwailem | F89: Not Started | G89: =I88 -> 46182 | H89: 14 | I89: =G89+H89 -> 46196 | J89: =IFERROR(MAX(0,MIN(1,(TODAY()-G89)/(I89-G89))),"") -> 0 | K89: 0
A90: Corporate Governance Setup | B90: Governance | C90: Shareholders Resolution (General Assembly) | D90: Shareholders undertake all resolutions (by unanimous written circular resolution or General Assembly) required to give effect to SHA terms (action also required for Aramco) | E90: Mawiyah Alqaed | F90: Not Started | G90: =I76-7 -> 46223 | H90: 7 | I90: =G90+H90 -> 46230 | J90: =IFERROR(MAX(0,MIN(1,(TODAY()-G90)/(I90-G90))),"") -> 0 | K90: 0
A91: Corporate Governance Setup | B91: Governance | C91: Inaugural Board meeting | D91: Prepare and conduct first Board meeting and approve foundational resolutions (e.g. company accession) | E91: Mawiyah Alqaed | F91: Not Started | G91: =G90+H90 -> 46230 | H91: 7 | I91: =G91+H91 -> 46237 | J91: =IFERROR(MAX(0,MIN(1,(TODAY()-G91)/(I91-G91))),"") -> 0 | K91: 0
A92: Corporate Governance Setup | B92: Governance | C92: Executive management transition plan | D92: Develop executive management transition support plan to support smooth handover from setup phase to operational governance | E92: Governance dept | F92: Not Started | G92: =I91 -> 46237 | H92: 21 | I92: =G92+H92 -> 46258 | J92: =IFERROR(MAX(0,MIN(1,(TODAY()-G92)/(I92-G92))),"") -> 0 | K92: 0
B93: Operational readiness | G93: =MIN(G94:G133) -> 46070 | H93: =I93-G93 -> 195 | I93: =MAX(I94:I133) -> 46265
A94: Operational readiness | B94: Finance | C94: Financial Policy Manual | D94: Identify policy required for JV to operate and develop Finance Policy Manual | E94: Hassen Moolla | F94: Not Started | G94: 46117 | H94: 21 | I94: =G94+H94 -> 46138 | J94: =IFERROR(MAX(0,MIN(1,(TODAY()-G94)/(I94-G94))),"") -> 0 | K94: 0
A95: Operational readiness | B95: Finance | C95: JV Financial KPIs | D95: Define Finance KPIs & monitor main performance measurement indicators | E95: Hassen Moolla | F95: Not Started | G95: 46117 | H95: 14 | I95: =G95+H95 -> 46131 | J95: =IFERROR(MAX(0,MIN(1,(TODAY()-G95)/(I95-G95))),"") -> 0 | K95: 0
A96: Operational readiness | B96: Finance | C96: Financial reporting templates | D96: Define standard monthly /quarterly financial report templates (including BoD, shareholders) and align with Aramco CFO | E96: Hassen Moolla | F96: Not Started | G96: =I95 -> 46131 | H96: 14 | I96: =G96+H96 -> 46145 | J96: =IFERROR(MAX(0,MIN(1,(TODAY()-G96)/(I96-G96))),"") -> 0 | K96: 0
A97: Operational readiness | B97: Finance | C97: Auditing principles | D97: Agree on external auditor selection criteria and process, define audit committee role, and confirm audit timeline for Year 1 | E97: Karim Mehboob | F97: Not Started | G97: 46117 | H97: 14 | I97: =G97+H97 -> 46131 | J97: =IFERROR(MAX(0,MIN(1,(TODAY()-G97)/(I97-G97))),"") -> 0 | K97: 0
A98: Operational readiness | B98: Finance | C98: External auditor selection | D98: Identify and shortlist external auditors, define scope of audit, present recommendation to Board for approval at inaugural meeting | E98: Karim Mehboob | F98: Not Started | G98: =I97 -> 46131 | H98: 60 | I98: =G98+H98 -> 46191 | J98: =IFERROR(MAX(0,MIN(1,(TODAY()-G98)/(I98-G98))),"") -> 0 | K98: 0
A99: Operational readiness | B99: Finance | C99: Initial Insurance protection | D99: Identify and procure insurance coverage for the JV (D&O liability, general liability, professional indemnity, property/equipment insurance for exploration activities) | E99: Hassen Moolla | F99: Not Started | G99: 46183 | H99: 14 | I99: =G99+H99 -> 46197 | J99: =IFERROR(MAX(0,MIN(1,(TODAY()-G99)/(I99-G99))),"") -> 0 | K99: 0
A100: Operational readiness | B100: Finance | C100: Corporate bank accounts | D100: Open bank accounts | E100: Marwan Sutan | F100: Not Started | G100: =I76 -> 46230 | H100: 21 | I100: =G100+H100 -> 46251 | J100: =IFERROR(MAX(0,MIN(1,(TODAY()-G100)/(I100-G100))),"") -> 0 | K100: 0
A101: Operational readiness | B101: Finance | C101: Bank signatory authorization | D101: Register authorized signatories | E101: Marwan Sutan | F101: Not Started | G101: =I76 -> 46230 | H101: 7 | I101: =G101+H101 -> 46237 | J101: =IFERROR(MAX(0,MIN(1,(TODAY()-G101)/(I101-G101))),"") -> 0 | K101: 0
...

Sheet Data Validation List
A1: Critical | B1: Status
A2: Yes | B2: Not Started
A3: No | B3: Delayed
B4: On-track
B5: Completed
