Workbook
Name POWER_USER_LINK_EDA81D4C_E424_4C6E_8A36_5F1A4994EB75: "Summary!R4C1:R17C2"

Sheet Cover
C7: Title | D7: Project Crystal - JV Day 1 Readiness Plan
C9: Description | D9: All actions required to achieve JV Day-1 operational readiness
C11: Date | D11: =TODAY() -> 46077

Sheet Summary
B2: REQUIREMENTS BY OWNER | C2: =SUM(C4:C29) -> 112 | D2: =SUM(D4:D29) -> 89 | E2: =SUM(E4:E29) -> 19 | F2: =SUM(F4:F29) -> 4 | G2: =SUM(G4:G29) -> 0 | I2: REQUIREMENTS BY WORKSTREAM | J2: =SUM(J4:J13) -> 116 | K2: =SUM(K4:K13) -> 93 | L2: =SUM(L4:L13) -> 19 | M2: =SUM(M4:M13) -> 4 | N2: =SUM(N4:N13) -> 0
B3: Owner | C3: Total | D3: Not started | E3: On-track | F3: Completed | G3: Delayed | I3: Workstream | J3: Total | K3: Not started | L3: On-track | M3: Completed | N3: Delayed
B4: Aseel Alnafea | C4: =SUM(D4:G4) -> 19 | D4: =(COUNTIFS('JV Readiness Plan'!$E:$E,$B4,'JV Readiness Plan'!$F:$F,D$3)) -> 19 | E4: =(COUNTIFS('JV Readiness Plan'!$E:$E,$B4,'JV Readiness Plan'!$F:$F,E$3)) -> 0 | F4: =(COUNTIFS('JV Readiness Plan'!$E:$E,$B4,'JV Readiness Plan'!$F:$F,F$3)) -> 0 | G4: =(COUNTIFS('JV Readiness Plan'!$E:$E,$B4,'JV Readiness Plan'!$F:$F,G$3)) -> 0 | I4: SHA | J4: =SUM(K4:N4) -> 46 | K4: =(COUNTIFS('JV Readiness Plan'!$A:$A,$I4,'JV Readiness Plan'!$F:$F,K$3)) -> 24 | L4: =(COUNTIFS('JV Readiness Plan'!$A:$A,$I4,'JV Readiness Plan'!$F:$F,L$3)) -> 18 | M4: =(COUNTIFS('JV Readiness Plan'!$A:$A,$I4,'JV Readiness Plan'!$F:$F,M$3)) -> 4 | N4: =(COUNTIFS('JV Readiness Plan'!$A:$A,$I4,'JV Readiness Plan'!$F:$F,N$3)) -> 0
B5: Muddassar | C5: =SUM(D5:G5) -> 14 | D5: =(COUNTIFS('JV Readiness Plan'!$E:$E,$B5,'JV Readiness Plan'!$F:$F,D$3)) -> 5 | E5: =(COUNTIFS('JV Readiness Plan'!$E:$E,$B5,'JV Readiness Plan'!$F:$F,E$3)) -> 7 | F5: =(COUNTIFS('JV Readiness Plan'!$E:$E,$B5,'JV Readiness Plan'!$F:$F,F$3)) -> 2 | G5: =(COUNTIFS('JV Readiness Plan'!$E:$E,$B5,'JV Readiness Plan'!$F:$F,G$3)) -> 0 | I5: Legal | J5: =SUM(K5:N5) -> 27 | K5: =(COUNTIFS('JV Readiness Plan'!$A:$A,$I5,'JV Readiness Plan'!$F:$F,K$3)) -> 27 | L5: =(COUNTIFS('JV Readiness Plan'!$A:$A,$I5,'JV Readiness Plan'!$F:$F,L$3)) -> 0 | M5: =(COUNTIFS('JV Readiness Plan'!$A:$A,$I5,'JV Readiness Plan'!$F:$F,M$3)) -> 0 | N5: =(COUNTIFS('JV Readiness Plan'!$A:$A,$I5,'JV Readiness Plan'!$F:$F,N$3)) -> 0
B6: Hassen Moolla | C6: =SUM(D6:G6) -> 13 | D6: =(COUNTIFS('JV Readiness Plan'!$E:$E,$B6,'JV Readiness Plan'!$F:$F,D$3)) -> 8 | E6: =(COUNTIFS('JV Readiness Plan'!$E:$E,$B6,'JV Readiness Plan'!$F:$F,E$3)) -> 4 | F6: =(COUNTIFS('JV Readiness Plan'!$E:$E,$B6,'JV Readiness Plan'!$F:$F,F$3)) -> 1 | G6: =(COUNTIFS('JV Readiness Plan'!$E:$E,$B6,'JV Readiness Plan'!$F:$F,G$3)) -> 0 | I6: Governance | J6: =SUM(K6:N6) -> 6 | K6: =(COUNTIFS('JV Readiness Plan'!$A:$A,$I6,'JV Readiness Plan'!$F:$F,K$3)) -> 6 | L6: =(COUNTIFS('JV Readiness Plan'!$A:$A,$I6,'JV Readiness Plan'!$F:$F,L$3)) -> 0 | M6: =(COUNTIFS('JV Readiness Plan'!$A:$A,$I6,'JV Readiness Plan'!$F:$F,M$3)) -> 0 | N6: =(COUNTIFS('JV Readiness Plan'!$A:$A,$I6,'JV Readiness Plan'!$F:$F,N$3)) -> 0
B7: Ramesh Murugesan | C7: =SUM(D7:G7) -> 10 | D7: =(COUNTIFS('JV Readiness Plan'!$E:$E,$B7,'JV Readiness Plan'!$F:$F,D$3)) -> 10 | E7: =(COUNTIFS('JV Readiness Plan'!$E:$E,$B7,'JV Readiness Plan'!$F:$F,E$3)) -> 0 | F7: =(COUNTIFS('JV Readiness Plan'!$E:$E,$B7,'JV Readiness Plan'!$F:$F,F$3)) -> 0 | G7: =(COUNTIFS('JV Readiness Plan'!$E:$E,$B7,'JV Readiness Plan'!$F:$F,G$3)) -> 0 | I7: Finance | J7: =SUM(K7:N7) -> 10 | K7: =(COUNTIFS('JV Readiness Plan'!$A:$A,$I7,'JV Readiness Plan'!$F:$F,K$3)) -> 10 | L7: =(COUNTIFS('JV Readiness Plan'!$A:$A,$I7,'JV Readiness Plan'!$F:$F,L$3)) -> 0 | M7: =(COUNTIFS('JV Readiness Plan'!$A:$A,$I7,'JV Readiness Plan'!$F:$F,M$3)) -> 0 | N7: =(COUNTIFS('JV Readiness Plan'!$A:$A,$I7,'JV Readiness Plan'!$F:$F,N$3)) -> 0
B8: Mawiyah Alqaed | C8: =SUM(D8:G8) -> 7 | D8: =(COUNTIFS('JV Readiness Plan'!$E:$E,$B8,'JV Readiness Plan'!$F:$F,D$3)) -> 6 | E8: =(COUNTIFS('JV Readiness Plan'!$E:$E,$B8,'JV Readiness Plan'!$F:$F,E$3)) -> 1 | F8: =(COUNTIFS('JV Readiness Plan'!$E:$E,$B8,'JV Readiness Plan'!$F:$F,F$3)) -> 0 | G8: =(COUNTIFS('JV Readiness Plan'!$E:$E,$B8,'JV Readiness Plan'!$F:$F,G$3)) -> 0 | I8: IT | J8: =SUM(K8:N8) -> 13 | K8: =(COUNTIFS('JV Readiness Plan'!$A:$A,$I8,'JV Readiness Plan'!$F:$F,K$3)) -> 12 | L8: =(COUNTIFS('JV Readiness Plan'!$A:$A,$I8,'JV Readiness Plan'!$F:$F,L$3)) -> 1 | M8: =(COUNTIFS('JV Readiness Plan'!$A:$A,$I8,'JV Readiness Plan'!$F:$F,M$3)) -> 0 | N8: =(COUNTIFS('JV Readiness Plan'!$A:$A,$I8,'JV Readiness Plan'!$F:$F,N$3)) -> 0
B9: Aseel Alnafea / Aramco Legal | C9: =SUM(D9:G9) -> 7 | D9: =(COUNTIFS('JV Readiness Plan'!$E:$E,$B9,'JV Readiness Plan'!$F:$F,D$3)) -> 7 | E9: =(COUNTIFS('JV Readiness Plan'!$E:$E,$B9,'JV Readiness Plan'!$F:$F,E$3)) -> 0 | F9: =(COUNTIFS('JV Readiness Plan'!$E:$E,$B9,'JV Readiness Plan'!$F:$F,F$3)) -> 0 | G9: =(COUNTIFS('JV Readiness Plan'!$E:$E,$B9,'JV Readiness Plan'!$F:$F,G$3)) -> 0 | I9: Procurement | J9: =SUM(K9:N9) -> 1 | K9: =(COUNTIFS('JV Readiness Plan'!$A:$A,$I9,'JV Readiness Plan'!$F:$F,K$3)) -> 1 | L9: =(COUNTIFS('JV Readiness Plan'!$A:$A,$I9,'JV Readiness Plan'!$F:$F,L$3)) -> 0 | M9: =(COUNTIFS('JV Readiness Plan'!$A:$A,$I9,'JV Readiness Plan'!$F:$F,M$3)) -> 0 | N9: =(COUNTIFS('JV Readiness Plan'!$A:$A,$I9,'JV Readiness Plan'!$F:$F,N$3)) -> 0
B10: Mohammed | C10: =SUM(D10:G10) -> 6 | D10: =(COUNTIFS('JV Readiness Plan'!$E:$E,$B10,'JV Readiness Plan'!$F:$F,D$3)) -> 4 | E10: =(COUNTIFS('JV Readiness Plan'!$E:$E,$B10,'JV Readiness Plan'!$F:$F,E$3)) -> 2 | F10: =(COUNTIFS('JV Readiness Plan'!$E:$E,$B10,'JV Readiness Plan'!$F:$F,F$3)) -> 0 | G10: =(COUNTIFS('JV Readiness Plan'!$E:$E,$B10,'JV Readiness Plan'!$F:$F,G$3)) -> 0 | I10: HR | J10: =SUM(K10:N10) -> 4 | K10: =(COUNTIFS('JV Readiness Plan'!$A:$A,$I10,'JV Readiness Plan'!$F:$F,K$3)) -> 4 | L10: =(COUNTIFS('JV Readiness Plan'!$A:$A,$I10,'JV Readiness Plan'!$F:$F,L$3)) -> 0 | M10: =(COUNTIFS('JV Readiness Plan'!$A:$A,$I10,'JV Readiness Plan'!$F:$F,M$3)) -> 0 | N10: =(COUNTIFS('JV Readiness Plan'!$A:$A,$I10,'JV Readiness Plan'!$F:$F,N$3)) -> 0
B11: Faraj Al Dossary | C11: =SUM(D11:G11) -> 6 | D11: =(COUNTIFS('JV Readiness Plan'!$E:$E,$B11,'JV Readiness Plan'!$F:$F,D$3)) -> 6 | E11: =(COUNTIFS('JV Readiness Plan'!$E:$E,$B11,'JV Readiness Plan'!$F:$F,E$3)) -> 0 | F11: =(COUNTIFS('JV Readiness Plan'!$E:$E,$B11,'JV Readiness Plan'!$F:$F,F$3)) -> 0 | G11: =(COUNTIFS('JV Readiness Plan'!$E:$E,$B11,'JV Readiness Plan'!$F:$F,G$3)) -> 0 | I11: HSSE | J11: =SUM(K11:N11) -> 5 | K11: =(COUNTIFS('JV Readiness Plan'!$A:$A,$I11,'JV Readiness Plan'!$F:$F,K$3)) -> 5 | L11: =(COUNTIFS('JV Readiness Plan'!$A:$A,$I11,'JV Readiness Plan'!$F:$F,L$3)) -> 0 | M11: =(COUNTIFS('JV Readiness Plan'!$A:$A,$I11,'JV Readiness Plan'!$F:$F,M$3)) -> 0 | N11: =(COUNTIFS('JV Readiness Plan'!$A:$A,$I11,'JV Readiness Plan'!$F:$F,N$3)) -> 0
B12: Rene Thumbran | C12: =SUM(D12:G12) -> 4 | D12: =(COUNTIFS('JV Readiness Plan'!$E:$E,$B12,'JV Readiness Plan'!$F:$F,D$3)) -> 2 | E12: =(COUNTIFS('JV Readiness Plan'!$E:$E,$B12,'JV Readiness Plan'!$F:$F,E$3)) -> 2 | F12: =(COUNTIFS('JV Readiness Plan'!$E:$E,$B12,'JV Readiness Plan'!$F:$F,F$3)) -> 0 | G12: =(COUNTIFS('JV Readiness Plan'!$E:$E,$B12,'JV Readiness Plan'!$F:$F,G$3)) -> 0 | I12: Comms | J12: =SUM(K12:N12) -> 3 | K12: =(COUNTIFS('JV Readiness Plan'!$A:$A,$I12,'JV Readiness Plan'!$F:$F,K$3)) -> 3 | L12: =(COUNTIFS('JV Readiness Plan'!$A:$A,$I12,'JV Readiness Plan'!$F:$F,L$3)) -> 0 | M12: =(COUNTIFS('JV Readiness Plan'!$A:$A,$I12,'JV Readiness Plan'!$F:$F,M$3)) -> 0 | N12: =(COUNTIFS('JV Readiness Plan'!$A:$A,$I12,'JV Readiness Plan'!$F:$F,N$3)) -> 0
B13: Muddassar / Mohammed | C13: =SUM(D13:G13) -> 3 | D13: =(COUNTIFS('JV Readiness Plan'!$E:$E,$B13,'JV Readiness Plan'!$F:$F,D$3)) -> 3 | E13: =(COUNTIFS('JV Readiness Plan'!$E:$E,$B13,'JV Readiness Plan'!$F:$F,E$3)) -> 0 | F13: =(COUNTIFS('JV Readiness Plan'!$E:$E,$B13,'JV Readiness Plan'!$F:$F,F$3)) -> 0 | G13: =(COUNTIFS('JV Readiness Plan'!$E:$E,$B13,'JV Readiness Plan'!$F:$F,G$3)) -> 0 | I13: Facilities | J13: =SUM(K13:N13) -> 1 | K13: =(COUNTIFS('JV Readiness Plan'!$A:$A,$I13,'JV Readiness Plan'!$F:$F,K$3)) -> 1 | L13: =(COUNTIFS('JV Readiness Plan'!$A:$A,$I13,'JV Readiness Plan'!$F:$F,L$3)) -> 0 | M13: =(COUNTIFS('JV Readiness Plan'!$A:$A,$I13,'JV Readiness Plan'!$F:$F,M$3)) -> 0 | N13: =(COUNTIFS('JV Readiness Plan'!$A:$A,$I13,'JV Readiness Plan'!$F:$F,N$3)) -> 0
B14: Susan Parker | C14: =SUM(D14:G14) -> 3 | D14: =(COUNTIFS('JV Readiness Plan'!$E:$E,$B14,'JV Readiness Plan'!$F:$F,D$3)) -> 3 | E14: =(COUNTIFS('JV Readiness Plan'!$E:$E,$B14,'JV Readiness Plan'!$F:$F,E$3)) -> 0 | F14: =(COUNTIFS('JV Readiness Plan'!$E:$E,$B14,'JV Readiness Plan'!$F:$F,F$3)) -> 0 | G14: =(COUNTIFS('JV Readiness Plan'!$E:$E,$B14,'JV Readiness Plan'!$F:$F,G$3)) -> 0
B15: Owen Hatton | C15: =SUM(D15:G15) -> 2 | D15: =(COUNTIFS('JV Readiness Plan'!$E:$E,$B15,'JV Readiness Plan'!$F:$F,D$3)) -> 0 | E15: =(COUNTIFS('JV Readiness Plan'!$E:$E,$B15,'JV Readiness Plan'!$F:$F,E$3)) -> 1 | F15: =(COUNTIFS('JV Readiness Plan'!$E:$E,$B15,'JV Readiness Plan'!$F:$F,F$3)) -> 1 | G15: =(COUNTIFS('JV Readiness Plan'!$E:$E,$B15,'JV Readiness Plan'!$F:$F,G$3)) -> 0
B16: Muddassar / Nuaim | C16: =SUM(D16:G16) -> 0 | D16: =(COUNTIFS('JV Readiness Plan'!$E:$E,$B16,'JV Readiness Plan'!$F:$F,D$3)) -> 0 | E16: =(COUNTIFS('JV Readiness Plan'!$E:$E,$B16,'JV Readiness Plan'!$F:$F,E$3)) -> 0 | F16: =(COUNTIFS('JV Readiness Plan'!$E:$E,$B16,'JV Readiness Plan'!$F:$F,F$3)) -> 0 | G16: =(COUNTIFS('JV Readiness Plan'!$E:$E,$B16,'JV Readiness Plan'!$F:$F,G$3)) -> 0
B17: Maaden and Aramco CEOs | C17: =SUM(D17:G17) -> 2 | D17: =(COUNTIFS('JV Readiness Plan'!$E:$E,$B17,'JV Readiness Plan'!$F:$F,D$3)) -> 2 | E17: =(COUNTIFS('JV Readiness Plan'!$E:$E,$B17,'JV Readiness Plan'!$F:$F,E$3)) -> 0 | F17: =(COUNTIFS('JV Readiness Plan'!$E:$E,$B17,'JV Readiness Plan'!$F:$F,F$3)) -> 0 | G17: =(COUNTIFS('JV Readiness Plan'!$E:$E,$B17,'JV Readiness Plan'!$F:$F,G$3)) -> 0
B18: Abdullah Alzamil | C18: =SUM(D18:G18) -> 2 | D18: =(COUNTIFS('JV Readiness Plan'!$E:$E,$B18,'JV Readiness Plan'!$F:$F,D$3)) -> 2 | E18: =(COUNTIFS('JV Readiness Plan'!$E:$E,$B18,'JV Readiness Plan'!$F:$F,E$3)) -> 0 | F18: =(COUNTIFS('JV Readiness Plan'!$E:$E,$B18,'JV Readiness Plan'!$F:$F,F$3)) -> 0 | G18: =(COUNTIFS('JV Readiness Plan'!$E:$E,$B18,'JV Readiness Plan'!$F:$F,G$3)) -> 0
B19: Hassen Moolla | C19: =SUM(D19:G19) -> 2 | D19: =(COUNTIFS('JV Readiness Plan'!$E:$E,$B19,'JV Readiness Plan'!$F:$F,D$3)) -> 2 | E19: =(COUNTIFS('JV Readiness Plan'!$E:$E,$B19,'JV Readiness Plan'!$F:$F,E$3)) -> 0 | F19: =(COUNTIFS('JV Readiness Plan'!$E:$E,$B19,'JV Readiness Plan'!$F:$F,F$3)) -> 0 | G19: =(COUNTIFS('JV Readiness Plan'!$E:$E,$B19,'JV Readiness Plan'!$F:$F,G$3)) -> 0
B20: Karim Mehboob | C20: =SUM(D20:G20) -> 2 | D20: =(COUNTIFS('JV Readiness Plan'!$E:$E,$B20,'JV Readiness Plan'!$F:$F,D$3)) -> 2 | E20: =(COUNTIFS('JV Readiness Plan'!$E:$E,$B20,'JV Readiness Plan'!$F:$F,E$3)) -> 0 | F20: =(COUNTIFS('JV Readiness Plan'!$E:$E,$B20,'JV Readiness Plan'!$F:$F,F$3)) -> 0 | G20: =(COUNTIFS('JV Readiness Plan'!$E:$E,$B20,'JV Readiness Plan'!$F:$F,G$3)) -> 0
B21: Marwan Sutan | C21: =SUM(D21:G21) -> 2 | D21: =(COUNTIFS('JV Readiness Plan'!$E:$E,$B21,'JV Readiness Plan'!$F:$F,D$3)) -> 2 | E21: =(COUNTIFS('JV Readiness Plan'!$E:$E,$B21,'JV Readiness Plan'!$F:$F,E$3)) -> 0 | F21: =(COUNTIFS('JV Readiness Plan'!$E:$E,$B21,'JV Readiness Plan'!$F:$F,F$3)) -> 0 | G21: =(COUNTIFS('JV Readiness Plan'!$E:$E,$B21,'JV Readiness Plan'!$F:$F,G$3)) -> 0
B22: Ramesh / Alex | C22: =SUM(D22:G22) -> 2 | D22: =(COUNTIFS('JV Readiness Plan'!$E:$E,$B22,'JV Readiness Plan'!$F:$F,D$3)) -> 1 | E22: =(COUNTIFS('JV Readiness Plan'!$E:$E,$B22,'JV Readiness Plan'!$F:$F,E$3)) -> 1 | F22: =(COUNTIFS('JV Readiness Plan'!$E:$E,$B22,'JV Readiness Plan'!$F:$F,F$3)) -> 0 | G22: =(COUNTIFS('JV Readiness Plan'!$E:$E,$B22,'JV Readiness Plan'!$F:$F,G$3)) -> 0
B23: Muddassar / Hassen | C23: =SUM(D23:G23) -> 1 | D23: =(COUNTIFS('JV Readiness Plan'!$E:$E,$B23,'JV Readiness Plan'!$F:$F,D$3)) -> 0 | E23: =(COUNTIFS('JV Readiness Plan'!$E:$E,$B23,'JV Readiness Plan'!$F:$F,E$3)) -> 1 | F23: =(COUNTIFS('JV Readiness Plan'!$E:$E,$B23,'JV Readiness Plan'!$F:$F,F$3)) -> 0 | G23: =(COUNTIFS('JV Readiness Plan'!$E:$E,$B23,'JV Readiness Plan'!$F:$F,G$3)) -> 0
B24: Aramco | C24: =SUM(D24:G24) -> 1 | D24: =(COUNTIFS('JV Readiness Plan'!$E:$E,$B24,'JV Readiness Plan'!$F:$F,D$3)) -> 1 | E24: =(COUNTIFS('JV Readiness Plan'!$E:$E,$B24,'JV Readiness Plan'!$F:$F,E$3)) -> 0 | F24: =(COUNTIFS('JV Readiness Plan'!$E:$E,$B24,'JV Readiness Plan'!$F:$F,F$3)) -> 0 | G24: =(COUNTIFS('JV Readiness Plan'!$E:$E,$B24,'JV Readiness Plan'!$F:$F,G$3)) -> 0
B25: Mawiyah Alqaed/Rene Thumbran? | C25: =SUM(D25:G25) -> 0 | D25: =(COUNTIFS('JV Readiness Plan'!$E:$E,$B25,'JV Readiness Plan'!$F:$F,D$3)) -> 0 | E25: =(COUNTIFS('JV Readiness Plan'!$E:$E,$B25,'JV Readiness Plan'!$F:$F,E$3)) -> 0 | F25: =(COUNTIFS('JV Readiness Plan'!$E:$E,$B25,'JV Readiness Plan'!$F:$F,F$3)) -> 0 | G25: =(COUNTIFS('JV Readiness Plan'!$E:$E,$B25,'JV Readiness Plan'!$F:$F,G$3)) -> 0
... B29: Raoof Madathil | C29: =SUM(D29:G29) -> 1 | D29: =(COUNTIFS('JV Readiness Plan'!$E:$E,$B29,'JV Readiness Plan'!$F:$F,D$3)) -> 1 | E29: =(COUNTIFS('JV Readiness Plan'!$E:$E,$B29,'JV Readiness Plan'!$F:$F,E$3)) -> 0 | F29: =(COUNTIFS('JV Readiness Plan'!$E:$E,$B29,'JV Readiness Plan'!$F:$F,F$3)) -> 0 | G29: =(COUNTIFS('JV Readiness Plan'!$E:$E,$B29,'JV Readiness Plan'!$F:$F,G$3)) -> 0

Sheet JV Readiness Plan
A1: PROJECT CRYSTAL - JV DAY-1 READINESS PLAN | H1: Day-1 target date | I1: =MAX(I4:I130) -> 46248
A3: Workstream | B3: Category | C3: Requirement | D3: Action | E3: Owner | F3: Status | G3: Start date | H3: Duration | I3: End date | J3: Target Completion (%) | K3: Notes
B4: Budget and Business Plan | G4: =MIN(G5:G13) -> 46054 | H4: =I4-G4 -> 51 | I4: =MAX(I5:I13) -> 46105
A5: SHA | B5: Budget and BP | C5: Align Roles, Responsibilities & Sources | D5: Clarify roles and responsibilities across Maaden finance and technical teams. Define who provides what, sources of information, and internal points of contact for each workstream. | E5: Hassen Moolla | F5: Completed | G5: 46054 | H5: 14 | I5: =G5+H5 -> 46068 | J5: =IFERROR(MAX(0,MIN(1,(TODAY()-G5)/(I5-G5))),"") -> 1
A6: SHA | B6: Budget and BP | C6: Identify Inputs & Assumptions | D6: Identify the full list of inputs and assumptions required to build the model. Define sources and providers for each item, and set deadlines for delivery. | E6: Hassen Moolla | F6: On-track | G6: =I5 -> 46068 | H6: 11 | I6: =G6+H6 -> 46079 | J6: =IFERROR(MAX(0,MIN(1,(TODAY()-G6)/(I6-G6))),"") -> 0.81818182
A7: SHA | B7: Budget and BP | C7: 5-Year Exploration Plan | D7: Develop 5-year Exploration Plan (2026-2030) | E7: Owen Hatton | F7: On-track | G7: =I5 -> 46068 | H7: 11 | I7: =G7+H7 -> 46079 | J7: =IFERROR(MAX(0,MIN(1,(TODAY()-G7)/(I7-G7))),"") -> 0.81818182
A8: SHA | B8: Budget and BP | C8: JV Day-1 Org Chart | D8: Finalize the Day-1 organization structure (confirm minimal technical staff requirements, including HSSE) | E8: Mohammed | F8: On-track | G8: 46071 | H8: 14 | I8: =G8+H8 -> 46085 | J8: =IFERROR(MAX(0,MIN(1,(TODAY()-G8)/(I8-G8))),"") -> 0.42857143
A9: SHA | B9: Budget and BP | C9: Build the Draft Model | D9: Construct the financial and operational model based on the defined inputs, assumptions, and agreed structure. Ensure formulas are robust and the model is auditable. | E9: Hassen Moolla | F9: Not Started | G9: =I7 -> 46079 | H9: 7 | I9: =G9+H9 -> 46086 | J9: =IFERROR(MAX(0,MIN(1,(TODAY()-G9)/(I9-G9))),"") -> 0
A10: SHA | B10: Budget and BP | C10: Validate with Key Maaden Stakeholders | D10: Present the draft model and BP outputs to key Maaden stakeholders (technical and finance) for review. Incorporate feedback and resolve any open items. | E10: Hassen Moolla | F10: Not Started | G10: =I9 -> 46086 | H10: 3 | I10: =G10+H10 -> 46089 | J10: =IFERROR(MAX(0,MIN(1,(TODAY()-G10)/(I10-G10))),"") -> 0
A11: SHA | B11: Budget and BP | C11: Package BP into Final Deliverable | D11: Define format/templates and develop final deliverables | E11: Hassen Moolla | F11: Not Started | G11: =I10 -> 46089 | H11: 7 | I11: =G11+H11 -> 46096 | J11: =IFERROR(MAX(0,MIN(1,(TODAY()-G11)/(I11-G11))),"") -> 0
A12: SHA | B12: Budget and BP | C12: BP Final Deliverable validation | D12: Validate final deliverables | E12: Mohammed | F12: Not Started | G12: =I11 -> 46096 | H12: 2 | I12: =G12+H12 -> 46098 | J12: =IFERROR(MAX(0,MIN(1,(TODAY()-G12)/(I12-G12))),"") -> 0
A13: SHA | B13: Budget and BP | C13: Obtain Feedback from Aramco & Update | D13: Share the finalized BP with Aramco for review. Collect feedback, incorporate agreed changes, and lock the final version for approval | E13: Mohammed | F13: Not Started | G13: =I12 -> 46098 | H13: 7 | I13: =G13+H13 -> 46105 | J13: =IFERROR(MAX(0,MIN(1,(TODAY()-G13)/(I13-G13))),"") -> 0
B14: TSA | G14: =MIN(G15:G20) -> 46054 | H14: =I14-G14 -> 63 | I14: =MAX(I15:I20) -> 46117
A15: SHA | B15: TSA | C15: Catalogue of technical services | D15: Develop the catalogue of technical services to be provided by Maaden to the JV under the TSA, identify what services are to be provided by 3d parties | E15: Owen Hatton | F15: Completed | G15: 46054 | H15: 11 | I15: =G15+H15 -> 46065 | J15: =IFERROR(MAX(0,MIN(1,(TODAY()-G15)/(I15-G15))),"") -> 1
A16: SHA | B16: TSA | C16: Charge-out rate | D16: Define the pricing methodology: establish the approach and basis for pricing each category of services (e.g., cost-plus, market benchmark, fixed fee) | E16: Hassen Moolla | F16: On-track | G16: =I15 -> 46065 | H16: 14 | I16: =G16+H16 -> 46079 | J16: =IFERROR(MAX(0,MIN(1,(TODAY()-G16)/(I16-G16))),"") -> 0.85714286
A17: SHA | B17: TSA | C17: Charge-out rate | D17: Apply the agreed pricing methodology to determine the applicable rates for each service in the catalogue | E17: Hassen Moolla | F17: Not Started | G17: =I16 -> 46079 | H17: 7 | I17: =G17+H17 -> 46086 | J17: =IFERROR(MAX(0,MIN(1,(TODAY()-G17)/(I17-G17))),"") -> 0
A18: SHA | B18: TSA | C18: Governance structure | D18: Define TSA governance structure and process: how TSA services are requested, approved, monitored, billed, paid, accounted (TSA management process) | E18: Muddassar / Nuaim / Aseel Alnafea | F18: Not Started | G18: 46082 | H18: 14 | I18: =G18+H18 -> 46096 | J18: =IFERROR(MAX(0,MIN(1,(TODAY()-G18)/(I18-G18))),"") -> 0 | K18: Waiting for Aramco's TSA - reference
A19: SHA | B19: TSA | C19: Legal framework | D19: Finalize the TSA legal framework: draft and agree on the legal terms and conditions governing the provision of services, including scope, performance standards, liability, and termination provisions | E19: Aseel Alnafea | F19: Not Started | G19: =I18 -> 46096 | H19: 14 | I19: =G19+H19 -> 46110 | J19: =IFERROR(MAX(0,MIN(1,(TODAY()-G19)/(I19-G19))),"") -> 0
A20: SHA | B20: TSA | C20: Obtain Feedback from Aramco & Update | D20: Share the finalized TSA version with Aramco for review. Collect feedback, incorporate agreed changes, and lock the final version for approval. | E20: Muddassar | F20: Not Started | G20: =I19 -> 46110 | H20: 7 | I20: =G20+H20 -> 46117 | J20: =IFERROR(MAX(0,MIN(1,(TODAY()-G20)/(I20-G20))),"") -> 0
B21: GSA | G21: =MIN(G22:G27) -> 46054 | H21: =I21-G21 -> 63 | I21: =MAX(I22:I27) -> 46117
A22: SHA | B22: GSA | C22: Catalogue of general services | D22: Develop the catalogue of services to be provided by Maaden to the JV under the GSA | E22: Hassen Moolla | F22: On-track | G22: 46054 | H22: 25 | I22: =G22+H22 -> 46079 | J22: =IFERROR(MAX(0,MIN(1,(TODAY()-G22)/(I22-G22))),"") -> 0.92
A23: SHA | B23: GSA | C23: Charge-out rate | D23: Define the pricing methodology: establish the approach and basis for pricing each category of services (e.g., cost-plus, market benchmark, fixed fee) | E23: Hassen Moolla | F23: On-track | G23: 46069 | H23: 10 | I23: =G23+H23 -> 46079 | J23: =IFERROR(MAX(0,MIN(1,(TODAY()-G23)/(I23-G23))),"") -> 0.8
A24: SHA | B24: GSA | C24: Charge-out rate | D24: Apply the agreed pricing methodology to determine the applicable rates for each service in the catalogue | E24: Hassen Moolla | F24: Not Started | G24: =I23 -> 46079 | H24: 7 | I24: =G24+H24 -> 46086 | J24: =IFERROR(MAX(0,MIN(1,(TODAY()-G24)/(I24-G24))),"") -> 0
A25: SHA | B25: GSA | C25: Governance structure | D25: Define GSA governance structure and process : how GSA services are requested, approved, monitored, billed, paid, accounted (GSA management process) | E25: Muddassar / Nuaim / Aseel Alnafea | F25: Not Started | G25: 46082 | H25: 14 | I25: =G25+H25 -> 46096 | J25: =IFERROR(MAX(0,MIN(1,(TODAY()-G25)/(I25-G25))),"") -> 0 | K25: Waiting for Aramco's TSA - reference
A26: SHA | B26: GSA | C26: Legal framework | D26: Finalize the GSA legal framework: draft and agree on the legal terms and conditions governing the provision of services, including scope, performance standards, liability, and termination provisions | E26: Aseel Alnafea | F26: Not Started | G26: =I25 -> 46096 | H26: 14 | I26: =G26+H26 -> 46110 | J26: =IFERROR(MAX(0,MIN(1,(TODAY()-G26)/(I26-G26))),"") -> 0
A27: SHA | B27: GSA | C27: Obtain Feedback from Aramco & Update | D27: Share the finalized TSA version with Aramco for review. Collect feedback, incorporate agreed changes, and lock the final version for approval | E27: Muddassar | F27: Not Started | G27: =I26 -> 46110 | H27: 7 | I27: =G27+H27 -> 46117 | J27: =IFERROR(MAX(0,MIN(1,(TODAY()-G27)/(I27-G27))),"") -> 0 | K27: STILL OPEN. Schedule 13 is completely empty. Each party needs to disclose their existing competing businesses. This is referenced in Clause 20.1(a)(i).STILL OPEN. Schedule 14 is completely empty. The funding notice templates need to be developed. Plus, the distinction between 'Form of Funding Notices' and 'Funding Request Notice template' is unclear in the SHA.
B28: DoA | G28: =MIN(G29:G31) -> 46068 | H28: =I28-G28 -> 37 | I28: =MAX(I29:I31) -> 46105
A29: SHA | B29: DoA | C29: Shareholders reference DoAs | D29: Obtain reference governance framework, obtain Maaden's existing Authority Matrix and Aramco's governance frameworks as benchmarks for the JV | E29: Mawiyah Alqaed | F29: Not Started | G29: 46077 | H29: 7 | I29: =G29+H29 -> 46084 | J29: =IFERROR(MAX(0,MIN(1,(TODAY()-G29)/(I29-G29))),"") -> 0
A30: SHA | B30: DoA | C30: Complete Design of DoA (Shedule 15) | D30: Design the multi-tiered financial approval matrix (incl governance and internal controls) : define approval tiers below Board thresholds across CAPEX, OPEX, contracts, procurement, HR, litigation, treasury, and asset management, aligned with SHA ceilings | E30: Mawiyah Alqaed | F30: On-track | G30: 46068 | H30: 30 | I30: =G30+H30 -> 46098 | J30: =IFERROR(MAX(0,MIN(1,(TODAY()-G30)/(I30-G30))),"") -> 0.3
A31: SHA | B31: DoA | C31: Obtain Feedback from Aramco & Update | D31: Share the finalized DoA version with Aramco for review. Collect feedback, incorporate agreed changes, and lock the final version for approval | E31: Muddassar / Mohammed | F31: Not Started | G31: =I30 -> 46098 | H31: 7 | I31: =G31+H31 -> 46105 | J31: =IFERROR(MAX(0,MIN(1,(TODAY()-G31)/(I31-G31))),"") -> 0
B32: Secondment | G32: =MIN(G33:G36) -> 46054 | H32: =I32-G32 -> 62 | I32: =MAX(I33:I36) -> 46116
A33: SHA | B33: Secondment | C33: Secondment framework | D33: Develop secondment framework agreement (duration, cost basis, reporting lines, benefits) | E33: Rene Thumbran | F33: On-track | G33: 46054 | H33: 40 | I33: =G33+H33 -> 46094 | J33: =IFERROR(MAX(0,MIN(1,(TODAY()-G33)/(I33-G33))),"") -> 0.575 | K33: Standard master framework
A34: SHA | B34: Secondment | C34: Allocation methodology | D34: Define cost allocation methodology and determine cost rates for secondees | E34: Rene Thumbran | F34: On-track | G34: 46055 | H34: 40 | I34: =G34+H34 -> 46095 | J34: =IFERROR(MAX(0,MIN(1,(TODAY()-G34)/(I34-G34))),"") -> 0.55
A35: SHA | B35: Secondment | C35: JV secondment agreement draft | D35: Draft JV secondment agreement | E35: Aseel Alnafea / Rene Thumbran | F35: Not Started | G35: =I34 -> 46095 | H35: 14 | I35: =G35+H35 -> 46109 | J35: =IFERROR(MAX(0,MIN(1,(TODAY()-G35)/(I35-G35))),"") -> 0
A36: SHA | B36: Secondment | C36: Obtain Feedback from Aramco & Update | D36: Share the finalized Secondment Agreement with Aramco for review. Collect feedback, incorporate agreed changes, and lock the final version for approval | E36: Muddassar / Mohammed | F36: Not Started | G36: =I35 -> 46109 | H36: 7 | I36: =G36+H36 -> 46116 | J36: =IFERROR(MAX(0,MIN(1,(TODAY()-G36)/(I36-G36))),"") -> 0
B37: SHA documentation | G37: =MIN(G38:G46) -> 46072 | H37: =I37-G37 -> 62 | I37: =MAX(I38:I46) -> 46134
A38: SHA | B38: SHA documentation | C38: Guarantee for Permitted Transfers | D38: Agree Form of Guarantee for Permitted Transfers (Schedule 10) | E38: Muddassar | F38: On-track | G38: 46072 | H38: 14 | I38: =G38+H38 -> 46086 | J38: =IFERROR(MAX(0,MIN(1,(TODAY()-G38)/(I38-G38))),"") -> 0.35714286 | K38: STILL OPEN. Schedule 10 is completely empty. Footnote 26 confirms this is still under discussion. Both parties need to agree on the form.
A39: SHA | B39: SHA documentation | C39: Finalization of the Agreement | D39: Finalize Form of Shareholder Services Agreement (Schedule 11) | E39: Muddassar | F39: On-track | G39: 46072 | H39: 14 | I39: =G39+H39 -> 46086 | J39: =IFERROR(MAX(0,MIN(1,(TODAY()-G39)/(I39-G39))),"") -> 0.35714286 | K39: STILL OPEN. Schedule 11 is entirely a placeholder. The substantive framework in Clause 21 exists, but the actual agreement form needs to be drafted. What exactly is this form? We understand GSA is a separament document, correct?
A40: SHA | B40: SHA documentation | C40: Economical assumptions | D40: Agree economic assumptions for technical studies (Schedule 16) - confirm applicability for Hard-Rock Exploration phase | E40: Muddassar | F40: On-track | G40: 46072 | H40: 14 | I40: =G40+H40 -> 46086 | J40: =IFERROR(MAX(0,MIN(1,(TODAY()-G40)/(I40-G40))),"") -> 0.35714286 | K40: CVA: do we really need this? This is only mentioned once on 15.12. Is this critical for SHA signing Mohammed: if needed, Muddassar to provide leveraging internal benchmarks (from other Maaden JVs?)
A41: SHA | B41: SHA documentation | C41: Competing business disclosure | D41: Complete existing competing businesses disclosure (Schedule 13) | E41: Aseel Alnafea / Aramco Legal | F41: Not Started | G41: 46077 | H41: 14 | I41: =G41+H41 -> 46091 | J41: =IFERROR(MAX(0,MIN(1,(TODAY()-G41)/(I41-G41))),"") -> 0 | K41: STILL OPEN. Schedule 13 is completely empty. Each party needs to disclose their existing competing businesses. This is referenced in Clause 20.1(a)(i).
A42: SHA | B42: SHA documentation | C42: Funding Notices | D42: Develop Form of Funding Notices, and standard Funding Request Notice template (Schedule 14) | E42: Muddassar / Hassen | F42: On-track | G42: 46072 | H42: 14 | I42: =G42+H42 -> 46086 | J42: =IFERROR(MAX(0,MIN(1,(TODAY()-G42)/(I42-G42))),"") -> 0.35714286 | K42: STILL OPEN. Schedule 14 is completely empty. The funding notice templates need to be developed. Plus, the distinction between 'Form of Funding Notices' and 'Funding Request Notice template' is unclear in the SHA.
A43: SHA | B43: SHA documentation | C43: Area of Interest and Transition Zone | D43: Provide all Area of Interest and Transition Zone maps and coordinates (Schedule 2) | E43: Mohammed | F43: On-track | G43: 46072 | H43: 14 | I43: =G43+H43 -> 46086 | J43: =IFERROR(MAX(0,MIN(1,(TODAY()-G43)/(I43-G43))),"") -> 0.35714286 | K43: Map in Part 1 is included, but all coordinate fields and the Transition Zone map remain as placeholders. Footnote 5 explicitly asks MDN to confirm.
A44: SHA | B44: SHA documentation | C44: Exploration License Assignment Agreeement | D44: Finalize Exploration License Assignment Agreeement | E44: Muddassar | F44: On-track | G44: 46072 | H44: 42 | I44: =G44+H44 -> 46114 | J44: =IFERROR(MAX(0,MIN(1,(TODAY()-G44)/(I44-G44))),"") -> 0.11904762 | K44: Is this a separate agreement, or should it be a SHA section/schedule? Is this the same as Exploration Services Agreement?
A45: SHA | B45: SHA documentation | C45: Exploration Services Agreement | D45: Finalize Exploration Services Agreement | E45: Muddassar | F45: On-track | G45: 46072 | H45: 42 | I45: =G45+H45 -> 46114 | J45: =IFERROR(MAX(0,MIN(1,(TODAY()-G45)/(I45-G45))),"") -> 0.11904762 | K45: Confirm with Aramco/Legal if this is Maaden's Technical Service Agreements or something else. Note: CVA validated full catalogue of technical services with Mohammed/Owen, next step: determine prices/SLAs with Abulrahman and Hassen
A46: SHA | B46: SHA documentation | C46: Obtain Feedback from Aramco & Update | D46: Share the final SHA documentation with Aramco for review. Collect feedback, incorporate agreed changes, and lock the final version for approval | E46: Muddassar / Mohammed | F46: Not Started | G46: =MAX(I38:I45) -> 46114 | H46: 20 | I46: =G46+H46 -> 46134 | J46: =IFERROR(MAX(0,MIN(1,(TODAY()-G46)/(I46-G46))),"") -> 0
B47: Corporate approval | G47: =MIN(G48:G56) -> 46061 | H47: =I47-G47 -> 100 | I47: =MAX(I48:I56) -> 46161
A48: SHA | B48: Corporate approval | C48: Maaden IC | D48: Prepare material and obtain approval at Maaden Investment Committee meeting | E48: Muddassar | F48: Completed | G48: 46061 | H48: 1 | I48: =G48+H48 -> 46062 | J48: =IFERROR(MAX(0,MIN(1,(TODAY()-G48)/(I48-G48))),"") -> 1
A49: SHA | B49: Corporate approval | C49: Maaden ExCom | D49: Prepare material and obtain approval at Maaden Excom meeting (Feb 17) | E49: Muddassar | F49: Completed | G49: 46070 | H49: 1 | I49: =G49+H49 -> 46071 | J49: =IFERROR(MAX(0,MIN(1,(TODAY()-G49)/(I49-G49))),"") -> 1
A50: SHA | B50: Corporate approval | C50: Maaden BoD | D50: Prepare material and obtain approval at BoD meeting (Mar 5) | E50: Muddassar | F50: Not Started | G50: 46086 | H50: 1 | I50: =G50+H50 -> 46087 | J50: =IFERROR(MAX(0,MIN(1,(TODAY()-G50)/(I50-G50))),"") -> 0 | K50: Incorporation resolution, Properly executed according to each Shareholder's internal corporate governance requirements, Likely notarized and legalized/apostilled for use in MOC
A51: SHA | B51: Corporate approval | C51: 365-Day Implementation Plan | D51: Draft 365 Day Implementation Plan | E51: Muddassar | F51: On-track | G51: 46076 | H51: 14 | I51: =G51+H51 -> 46090 | J51: =IFERROR(MAX(0,MIN(1,(TODAY()-G51)/(I51-G51))),"") -> 0.071428571
A52: SHA | B52: Corporate approval | C52: 365-Day Implementation Plan | D52: Share the finalized Plan with Aramco for review. Collect feedback, incorporate agreed changes, and lock the final version for approval | E52: Muddassar | F52: Not Started | G52: =I51 -> 46090 | H52: 7 | I52: =G52+H52 -> 46097 | J52: =IFERROR(MAX(0,MIN(1,(TODAY()-G52)/(I52-G52))),"") -> 0
A53: SHA | B53: Corporate approval | C53: 5-year Implementation Plan | D53: Draft JV Long-term Implementation Plan (key milestones) | E53: Muddassar | F53: On-track | G53: 46076 | H53: 14 | I53: =G53+H53 -> 46090 | J53: =IFERROR(MAX(0,MIN(1,(TODAY()-G53)/(I53-G53))),"") -> 0.071428571
A54: SHA | B54: Corporate approval | C54: 5-year Implementation Plan | D54: Share the finalized Plan with Aramco for review. Collect feedback, incorporate agreed changes, and lock the final version for approval | E54: Muddassar | F54: Not Started | G54: =I53 -> 46090 | H54: 7 | I54: =G54+H54 -> 46097 | J54: =IFERROR(MAX(0,MIN(1,(TODAY()-G54)/(I54-G54))),"") -> 0
A55: SHA | B55: Corporate approval | C55: Board of Directors Aramco | D55: Obtain approval at BoD meeting (mid-May) | E55: Aramco | F55: Not Started | G55: 46156 | H55: 1 | I55: =G55+H55 -> 46157 | J55: =IFERROR(MAX(0,MIN(1,(TODAY()-G55)/(I55-G55))),"") -> 0
A56: SHA | B56: Corporate approval | C56: SHA signed by both Shareholders | D56: Sign Shareholder Agreement | E56: Maaden and Aramco CEOs | F56: Not Started | G56: =I55 -> 46157 | H56: 4 | I56: =G56+H56 -> 46161 | J56: =IFERROR(MAX(0,MIN(1,(TODAY()-G56)/(I56-G56))),"") -> 0 | K56: Need to confirme timeline and what is prerequisite for signing and what can be handled as CP. This is the final deliverable. Potential key blockers: multiple empty schedules, numerous 'Note to Draft' items, outstanding commercial terms
B57: Entity Formation | G57: =MIN(G58:G75) -> 46082 | H57: =I57-G57 -> 131 | I57: =MAX(I58:I75) -> 46213
A58: Legal | B58: Entity Formation | C58: Power of Attorney (PoA) | D58: Issue legalized power of attorney authorizing Kingdom representatives before MOC and SBC | E58: Aseel Alnafea / Aramco Legal | F58: Not Started | G58: 46082 | H58: 14 | I58: =G58+H58 -> 46096 | J58: =IFERROR(MAX(0,MIN(1,(TODAY()-G58)/(I58-G58))),"") -> 0 | K58: authorize representatives before MOC and SBC (Maaden issued, Aramco pending)
A59: Legal | B59: Entity Formation | C59: Trade name reservation | D59: Submit reservation of Trade name with Saudi Business Center (SBC), and obtain name approval from MOC | E59: Aseel Alnafea | F59: Not Started | G59: =I58 -> 46096 | H59: 7 | I59: =G59+H59 -> 46103 | J59: =IFERROR(MAX(0,MIN(1,(TODAY()-G59)/(I59-G59))),"") -> 0 | K59: 24 hours (in MPP ithe timeline is 5-10 business days) A commercial name reservation remains valid for only 60 days but may be renewed prior to expiry.
A60: Legal | B60: Entity Formation | C60: Constitutional documents | D60: Gather constitutional documents and Financial Statements (e.g., certificate of incorporation and articles (or equivalent) and audited financial statements of each Shareholder | E60: Aseel Alnafea | F60: Not Started | G60: 46096 | H60: 14 | I60: =G60+H60 -> 46110 | J60: =IFERROR(MAX(0,MIN(1,(TODAY()-G60)/(I60-G60))),"") -> 0 | K60: Based on the SHA document, for MOC/SBC approval of AoA
A61: Governance | B61: Corporate Governance Setup | C61: Initial Board remuneration | D61: Define initial remuneration for Board Memebrs | E61: Mawiyah Alqaed/Aramco Governance | F61: Not Started | G61: 46082 | H61: 14 | I61: =G61+H61 -> 46096 | J61: =IFERROR(MAX(0,MIN(1,(TODAY()-G61)/(I61-G61))),"") -> 0
A62: Legal | B62: Entity Formation | C62: Board members nomination | D62: Both shareholders nominate board members | E62: Maaden and Aramco CEOs | F62: Not Started | G62: 46114 | H62: 21 | I62: =G62+H62 -> 46135 | J62: =IFERROR(MAX(0,MIN(1,(TODAY()-G62)/(I62-G62))),"") -> 0
A63: Legal | B63: Entity Formation | C63: Board members’ and GM information | D63: Gather - from each board member and GM - a copy of passport/ID and contact information for MoC | E63: Aseel Alnafea / Aramco Legal | F63: Not Started | G63: =I62 -> 46135 | H63: 7 | I63: =G63+H63 -> 46142 | J63: =IFERROR(MAX(0,MIN(1,(TODAY()-G63)/(I63-G63))),"") -> 0 | K63: Source: Steps Plan - company incorporation
A64: Legal | B64: Entity Formation | C64: Details of the ultimate beneficiary(ies) for MOC | D64: Gather information of the ultimate beneficiaries for Ministry of Commerce | E64: Aseel Alnafea | F64: Not Started | G64: 46142 | H64: 14 | I64: =G64+H64 -> 46156 | J64: =IFERROR(MAX(0,MIN(1,(TODAY()-G64)/(I64-G64))),"") -> 0 | K64: For and Aramco, since it is a listed joint stock company, the following information would be required for the natural person having the authority to represent in general assemblies of companies owned by Maaden: • Full name. • ID number. • Date and place of birth. • Nationality. • National address. • Phone number. • Email address (if any).
A65: Legal | B65: Entity Formation | C65: Board members/GM appointment consent | D65: Board members and GM to approve their appointment - completed via Absher digital system | E65: Aseel Alnafea / Aramco Legal | F65: Not Started | G65: =I56 -> 46161 | H65: 7 | I65: =G65+H65 -> 46168 | J65: =IFERROR(MAX(0,MIN(1,(TODAY()-G65)/(I65-G65))),"") -> 0 | K65: For KSA nationals/residents, approval can be made: •electronically through a onetime password sent to the phone number registered with the KSA authorities, which can be shared with CC at the relevant time; or •in writing by signing a consent letter and authenticating the signature before: (i) the Chamber of Commerce; (ii) MOC; or (iii) a KSA licensed bank. • For non-KSA nationals/residents, approval can be made in writing by signing a consent letter and authenticating the signature by apostille or notarization and legalization up to the level of the KSA embassy and the Ministry of Foreign Affairs.
A66: Legal | B66: Entity Formation | C66: GAC no-notification application form | D66: Prepare GAC no-notification application form to be submitted to the GAC | E66: Aseel Alnafea | F66: Not Started | G66: 46127 | H66: 7 | I66: =G66+H66 -> 46134 | J66: =IFERROR(MAX(0,MIN(1,(TODAY()-G66)/(I66-G66))),"") -> 0 | K66: Critical path , prior to AoA notarization and CR issuing. waiting period up to 90 days, it will require a significant pack of documents: signed SHA, transaction description, copies of CR, AoA of the mother companies, org chart of the mother companies,audited finance reports…
A67: Legal | B67: Entity Formation | C67: GAC no-notification economic report | D67: Submit GAC no-notification economic report | E67: Aseel Alnafea | F67: Not Started | G67: 46127 | H67: 7 | I67: =G67+H67 -> 46134 | J67: =IFERROR(MAX(0,MIN(1,(TODAY()-G67)/(I67-G67))),"") -> 0
A68: Legal | B68: Entity Formation | C68: GAC approval | D68: Apply for and receive all required antitrust approvals (including GAC confirmation of non-applicability) | E68: Aseel Alnafea | F68: Not Started | G68: =I56 -> 46161 | H68: 43 | I68: =G68+H68 -> 46204 | J68: =IFERROR(MAX(0,MIN(1,(TODAY()-G68)/(I68-G68))),"") -> 0
A69: Legal | B69: Entity Formation | C69: Board appointment resolutions | D69: Each Shareholder formally approves the appointment of their nominated Directors | E69: Aseel Alnafea / Aramco Legal | F69: Not Started | G69: =I56 -> 46161 | H69: 7 | I69: =G69+H69 -> 46168 | J69: =IFERROR(MAX(0,MIN(1,(TODAY()-G69)/(I69-G69))),"") -> 0 | K69: Schedule 12, Part 2, paragraph 3.1 requires that at least three (3) Business Days prior to the Commencement Date, each Shareholder must deliver to the other a written Shareholders' resolution approving the appointment of their respective Directors in accordance with Clause 6.
A70: Legal | B70: Entity Formation | C70: Articles of Association drafting | D70: Draft AoA incorporating SHA terms and get shareholders approval | E70: Aseel Alnafea / Aramco Legal | F70: Not Started | G70: 46127 | H70: 21 | I70: =G70+H70 -> 46148 | J70: =IFERROR(MAX(0,MIN(1,(TODAY()-G70)/(I70-G70))),"") -> 0 | K70: (paragraph 2.1.2(d) of Part 2, Schedule 12) Arabic, per MOC template
A71: Legal | B71: Entity Formation | C71: Articles of Association approval | D71: Submit AoA through SBC Portal (MOC) for MOC approval | E71: Aseel Alnafea | F71: Not Started | G71: =I70 -> 46148 | H71: 21 | I71: =G71+H71 -> 46169 | J71: =IFERROR(MAX(0,MIN(1,(TODAY()-G71)/(I71-G71))),"") -> 0 | K71: 2-3 weeks for MOC review. At the Commencement date SHaholders exchange signed SHA and transactional documents (Secondment Agreement, GSAs, TSAs, ESA) On the Commencement Date, the AoA are signed before MOC/SBC, shares are issued, and the entity comes into existence. The directors named in those pre-completion resolutions are effectively the initial directors.
A72: Legal | B72: Entity Formation | C72: AoA signing | D72: Sign AoA before MOC/SBC official (via SBC portal) | E72: Aseel Alnafea / Aramco Legal | F72: Not Started | G72: =I68 -> 46204 | H72: 1 | I72: =G72+H72 -> 46205 | J72: =IFERROR(MAX(0,MIN(1,(TODAY()-G72)/(I72-G72))),"") -> 0 | K72: At the Commencement date SHaholders exchange signed SHA and transactional documents (Secondment Agreement, GSAs, TSAs, ESA)On the Commencement Date, the AoA are signed before MOC/SBC, shares are issued, and the entity comes into existence. The directors named in those pre-completion resolutions are effectively the initial directors.
A73: Legal | B73: Entity Formation | C73: AoA issuing | D73: Complete payment of the MOC application and publication fees, Deliver Articles of Association issued electronically via the SBC portal | E73: Aseel Alnafea | F73: Not Started | G73: =I72 -> 46205 | H73: 2 | I73: =G73+H73 -> 46207 | J73: =IFERROR(MAX(0,MIN(1,(TODAY()-G73)/(I73-G73))),"") -> 0 | K73: Payment of the relevant application fees must be made through SADAD within a period to be specified in an invoice to be issued by MOC; otherwise, the application will be cancelled automatically. MOC typically publishes the articles of association within 24 hours after the payment has been made.
A74: Legal | B74: Entity Formation | C74: Board Members Registration with MOC | D74: Formally register all directors with MOC | E74: Aseel Alnafea | F74: Not Started | G74: =I73 -> 46207 | H74: 3 | I74: =G74+H74 -> 46210 | J74: =IFERROR(MAX(0,MIN(1,(TODAY()-G74)/(I74-G74))),"") -> 0
A75: Legal | B75: Entity Formation | C75: Commercial Registration (CR) | D75: Obtain CR from Ministry of Commerce | E75: Aseel Alnafea | F75: Not Started | G75: =I74 -> 46210 | H75: 3 | I75: =G75+H75 -> 46213 | J75: =IFERROR(MAX(0,MIN(1,(TODAY()-G75)/(I75-G75))),"") -> 0 | K75: Critical path - unlocks everything
B76: Post-formation registration | G76: =MIN(G77:G86) -> 46213 | H76: =I76-G76 -> 14 | I76: =MAX(I77:I86) -> 46227
A77: Legal | B77: Post-formation registration | C77: Chamber of Commerce registration | D77: Register with local Chamber of Commerce | E77: Aseel Alnafea | F77: Not Started | G77: =I75 -> 46213 | H77: 7 | I77: =G77+H77 -> 46220 | J77: =IFERROR(MAX(0,MIN(1,(TODAY()-G77)/(I77-G77))),"") -> 0
A78: Legal | B78: Post-formation registration | C78: ZAKAT, TAX and Customs registration | D78: Register with the ZAKAT, Tax and Customs Authority | E78: Abdullah Alzamil | F78: Not Started | G78: =I75 -> 46213 | H78: 7 | I78: =G78+H78 -> 46220 | J78: =IFERROR(MAX(0,MIN(1,(TODAY()-G78)/(I78-G78))),"") -> 0 | K78: Required for invoicing
A79: Legal | B79: Post-formation registration | C79: VAT registration | D79: Register for VAT with ZATCA | E79: Abdullah Alzamil | F79: Not Started | G79: =I75 -> 46213 | H79: 14 | I79: =G79+H79 -> 46227 | J79: =IFERROR(MAX(0,MIN(1,(TODAY()-G79)/(I79-G79))),"") -> 0
A80: Legal | B80: Post-formation registration | C80: GOSI registration | D80: Register with General Organization for Social Insurance (GOSI) | E80: Aseel Alnafea | F80: Not Started | G80: =I75 -> 46213 | H80: 7 | I80: =G80+H80 -> 46220 | J80: =IFERROR(MAX(0,MIN(1,(TODAY()-G80)/(I80-G80))),"") -> 0 | K80: Required before hiring
A81: Legal | B81: Post-formation registration | C81: MHRSD registration | D81: Register with Ministry of Human Resources (MHRSD) | E81: Aseel Alnafea | F81: Not Started | G81: =I75 -> 46213 | H81: 7 | I81: =G81+H81 -> 46220 | J81: =IFERROR(MAX(0,MIN(1,(TODAY()-G81)/(I81-G81))),"") -> 0 | K81: Labor law compliance
A82: Legal | B82: Post-formation registration | C82: Saudi Post Registration | D82: Registration with the Saudi Post Office | E82: Aseel Alnafea | F82: Not Started | G82: =I75 -> 46213 | H82: 7 | I82: =G82+H82 -> 46220 | J82: =IFERROR(MAX(0,MIN(1,(TODAY()-G82)/(I82-G82))),"") -> 0
A83: Legal | B83: Post-formation registration | C83: Municipality License | D83: Obtain a municipality License from Ministry of Municipal and Rural Affairs | E83: Aseel Alnafea | F83: Not Started | G83: =I75 -> 46213 | H83: 14 | I83: =G83+H83 -> 46227 | J83: =IFERROR(MAX(0,MIN(1,(TODAY()-G83)/(I83-G83))),"") -> 0
A84: Legal | B84: Post-formation registration | C84: Nitaqat classification | D84: Obtain initial Saudization classification | E84: Aseel Alnafea | F84: Not Started | G84: =I75 -> 46213 | H84: 14 | I84: =G84+H84 -> 46227 | J84: =IFERROR(MAX(0,MIN(1,(TODAY()-G84)/(I84-G84))),"") -> 0
A85: Legal | B85: Post-formation registration | C85: Civil Defence Certificate | D85: Obtain a Civil Defence Certificate, as necessary | E85: Faraj Al Dossary | F85: Not Started | G85: =I75 -> 46213 | H85: 14 | I85: =G85+H85 -> 46227 | J85: =IFERROR(MAX(0,MIN(1,(TODAY()-G85)/(I85-G85))),"") -> 0
A86: Legal | B86: Post-formation registration | C86: Other licenses and registrations | D86: Obtain all other operational licenses and registrations (e.g. licenses from the MIMR) | E86: Aseel Alnafea | F86: Not Started | G86: =I75 -> 46213 | H86: 14 | I86: =G86+H86 -> 46227 | J86: =IFERROR(MAX(0,MIN(1,(TODAY()-G86)/(I86-G86))),"") -> 0
B87: Corporate Governance Setup | G87: =MIN(G88:G92) -> 46161 | H87: =I87-G87 -> 70 | I87: =MAX(I88:I92) -> 46231
A88: Governance | B88: Corporate Governance Setup | C88: BoD Charter | D88: Develop BoD Charter (incl. board composition, committees, authority matrices, voting & veto rights, exec management governance, performance assessment) | E88: Mawiyah Alqaed | F88: Not Started | G88: =I56 -> 46161 | H88: 21 | I88: =G88+H88 -> 46182 | J88: =IFERROR(MAX(0,MIN(1,(TODAY()-G88)/(I88-G88))),"") -> 0
A89: Governance | B89: Corporate Governance Setup | C89: Board of Directors on-boarding | D89: Prepare on-boarding documentation for JV Board of Directors | E89: Mawiyah Alqaed | F89: Not Started | G89: =I88 -> 46182 | H89: 14 | I89: =G89+H89 -> 46196 | J89: =IFERROR(MAX(0,MIN(1,(TODAY()-G89)/(I89-G89))),"") -> 0
A90: Governance | B90: Corporate Governance Setup | C90: Shareholders Resolution (General Assembly) | D90: Shareholders undertake all resolutions (by unanimous written circular resolution or General Assembly) required to give effect to SHA terms | E90: Mawiyah Alqaed | F90: Not Started | G90: =I75-7 -> 46206 | H90: 7 | I90: =G90+H90 -> 46213 | J90: =IFERROR(MAX(0,MIN(1,(TODAY()-G90)/(I90-G90))),"") -> 0 | K90: Per SHA Clause 3.1(b)
A91: Governance | B91: Corporate Governance Setup | C91: Inaugural Board meeting | D91: Prepare and conduct first Board meeting and approve foundational resolutions (e.g. company accession) | E91: Mawiyah Alqaed | F91: Not Started | G91: =I74-7 -> 46203 | H91: 7 | I91: =G91+H91 -> 46210 | J91: =IFERROR(MAX(0,MIN(1,(TODAY()-G91)/(I91-G91))),"") -> 0 | K91: First Board Meeting — Must Resolve: Appoint Management TeamCEO, CFO, GM of Exploration, Financial Controller Open bank account With KSA-licensed bank Ratify Initial Budget and Business Plan Adopt Related Agreements GSAs, TSA, Secondment, Exploration Services Adopt Company policies HR, finance, procurement, etc.Adopt Initial Authority MatrixDelegation of authority framework
A92: Governance | B92: Corporate Governance Setup | C92: Executive management transition plan | D92: Develop executive management transition support plan to support smooth handover from setup phase to operational governance | E92: Mawiyah Alqaed | F92: Not Started | G92: =I91 -> 46210 | H92: 21 | I92: =G92+H92 -> 46231 | J92: =IFERROR(MAX(0,MIN(1,(TODAY()-G92)/(I92-G92))),"") -> 0 | K92: First Board Meeting — Must Resolve: Appoint Management TeamCEO, CFO, GM of Exploration, Financial Controller Open bank account With KSA-licensed bank Ratify Initial Budget and Business Plan Adopt Related Agreements GSAs, TSA, Secondment, Exploration Services Adopt Company policies HR, finance, procurement, etc.Adopt Initial Authority MatrixDelegation of authority framework
B93: Operational readiness | G93: =MIN(G94:G130) -> 46070 | H93: =I93-G93 -> 178 | I93: =MAX(I94:I130) -> 46248
A94: Finance | B94: Policies | C94: Finance Policy Manual | D94: Identify policy required for JV to operate and develop Finance Policy Manual | E94: Hassen Moolla | F94: Not Started | G94: 46117 | H94: 21 | I94: =G94+H94 -> 46138 | J94: =IFERROR(MAX(0,MIN(1,(TODAY()-G94)/(I94-G94))),"") -> 0 | K94: Leverage Maaden accounting policy manual, maaden exploration procedure manual to be adopted by JV,
A95: Finance | B95: Reporting | C95: Finance performance management | D95: Define Finance KPIs & monitor main performance measurement indicators | E95: Hassen Moolla | F95: Not Started | G95: 46117 | H95: 14 | I95: =G95+H95 -> 46131 | J95: =IFERROR(MAX(0,MIN(1,(TODAY()-G95)/(I95-G95))),"") -> 0
A96: Finance | B96: Reporting | C96: Reporting templates | D96: Define standard monthly /quarterly financial report templates (including BoD, shareholders) and align with Aramco CFO | E96: Hassen Moolla | F96: Not Started | G96: =I95 -> 46131 | H96: 14 | I96: =G96+H96 -> 46145 | J96: =IFERROR(MAX(0,MIN(1,(TODAY()-G96)/(I96-G96))),"") -> 0
A97: Finance | B97: Auditing | C97: Define auditing principles | D97: Agree on external auditor selection criteria and process, define audit committee role, and confirm audit timeline for Year 1 | E97: Karim Mehboob | F97: Not Started | G97: 46117 | H97: 14 | I97: =G97+H97 -> 46131 | J97: =IFERROR(MAX(0,MIN(1,(TODAY()-G97)/(I97-G97))),"") -> 0
A98: Finance | B98: Auditing | C98: External auditor selection | D98: Identify and shortlist external auditors, define scope of audit, present recommendation to Board for approval at inaugural meeting | E98: Karim Mehboob | F98: Not Started | G98: =I97 -> 46131 | H98: 60 | I98: =G98+H98 -> 46191 | J98: =IFERROR(MAX(0,MIN(1,(TODAY()-G98)/(I98-G98))),"") -> 0
A99: Finance | B99: Treasury | C99: Initial Insurance protection | D99: Identify and procure insurance coverage for the JV (D&O liability, general liability, professional indemnity, property/equipment insurance for exploration activities) | E99: Hassen Moolla | F99: Not Started | G99: 46183 | H99: 14 | I99: =G99+H99 -> 46197 | J99: =IFERROR(MAX(0,MIN(1,(TODAY()-G99)/(I99-G99))),"") -> 0
A100: Finance | B100: Treasury | C100: Corporate bank accounts | D100: Open bank accounts | E100: Marwan Sutan | F100: Not Started | G100: =I75 -> 46213 | H100: 21 | I100: =G100+H100 -> 46234 | J100: =IFERROR(MAX(0,MIN(1,(TODAY()-G100)/(I100-G100))),"") -> 0 | K100: Requires Commercial Registration (CR), Article of Association (AoA), Board Resolution, Board Bank Delegation of Authority, Bank KYC process → 2-4 weeks typically
A101: Finance | B101: Treasury | C101: Bank signatory authorization | D101: Register authorized signatories | E101: Marwan Sutan | F101: Not Started | G101: =I75 -> 46213 | H101: 7 | I101: =G101+H101 -> 46220 | J101: =IFERROR(MAX(0,MIN(1,(TODAY()-G101)/(I101-G101))),"") -> 0 | K101: Need GM appointed,
...

Sheet Data Validation List
A1: Critical | B1: Status
A2: Yes | B2: Not Started
A3: No | B3: Delayed
B4: On-track
B5: Completed
